{
	"fileHeader": [
		{
			"fileIndex": 1,
			"fileID": "22CF9000",
			"unk": 11,
			"extension": "dat",
			"isCompressed": true,
			"compressedUnk": 0
		},
		{
			"fileIndex": 2,
			"fileID": "7DE05C00",
			"unk": 11,
			"extension": "dat",
			"isCompressed": true,
			"compressedUnk": 0
		},
		{
			"fileIndex": 3,
			"fileID": "6F901C00",
			"unk": 11,
			"extension": "dat",
			"isCompressed": true,
			"compressedUnk": 0
		},
		{
			"fileIndex": 4,
			"fileID": "B41BCC00",
			"unk": 11,
			"extension": "dat",
			"isCompressed": true,
			"compressedUnk": 0
		},
		{
			"fileIndex": 5,
			"fileID": "7495BC00",
			"unk": 11,
			"extension": "dat",
			"isCompressed": true,
			"compressedUnk": 0
		},
		{
			"fileIndex": 6,
			"fileID": "44A98800",
			"unk": 11,
			"extension": "dat",
			"isCompressed": true,
			"compressedUnk": 0
		},
		{
			"fileIndex": 7,
			"fileID": "50B18800",
			"unk": 11,
			"extension": "dat",
			"isCompressed": true,
			"compressedUnk": 0
		},
		{
			"fileIndex": 8,
			"fileID": "2A0EA000",
			"unk": 11,
			"extension": "dat",
			"isCompressed": true,
			"compressedUnk": 0
		},
		{
			"fileIndex": 9,
			"fileID": "17B5FC00",
			"unk": 11,
			"extension": "dat",
			"isCompressed": true,
			"compressedUnk": 0
		},
		{
			"fileIndex": 10,
			"fileID": "3503C000",
			"unk": 11,
			"extension": "dat",
			"isCompressed": true,
			"compressedUnk": 0
		},
		{
			"fileIndex": 11,
			"fileID": "524B3C00",
			"unk": 11,
			"extension": "dat",
			"isCompressed": true,
			"compressedUnk": 0
		},
		{
			"fileIndex": 12,
			"fileID": "E452FC00",
			"unk": 11,
			"extension": "dat",
			"isCompressed": true,
			"compressedUnk": 0
		},
		{
			"fileIndex": 13,
			"fileID": "63FC2400",
			"unk": 11,
			"extension": "dat",
			"isCompressed": true,
			"compressedUnk": 0
		},
		{
			"fileIndex": 14,
			"fileID": "5532BC00",
			"unk": 11,
			"extension": "dat",
			"isCompressed": true,
			"compressedUnk": 0
		},
		{
			"fileIndex": 15,
			"fileID": "3918FC00",
			"unk": 11,
			"extension": "dat",
			"isCompressed": true,
			"compressedUnk": 0
		},
		{
			"fileIndex": 16,
			"fileID": "F01A6C00",
			"unk": 11,
			"extension": "dat",
			"isCompressed": true,
			"compressedUnk": 0
		},
		{
			"fileIndex": 17,
			"fileID": "EF98AC00",
			"unk": 11,
			"extension": "dat",
			"isCompressed": true,
			"compressedUnk": 0
		}
	],
	"archiveHeader": {
		"ver": 10
	}
}
