{
	"header": {
		"text_amount": 141,
		"unk1": 12,
		"header_size": 64,
		"script_section_size": 41583,
		"offset_strings": 41648,
		"strings_section_size1": 1692,
		"offset3": 43344,
		"section_size2": 564,
		"offset4": 43920,
		"section_size3": 16,
		"offset5": 43936,
		"section_size4": 284,
		"unk3": 0,
		"offset6": 41574,
		"offset7": 41582,
		"unk4": 0
	},
	"text_info": [
		{
			"text_contents": "<17\u0003>{8, MessageNpcName, +}<2F耀>{4, message}のお願いを聞きますか？",
			"hasEntryInOffsetOffsets": true,
			"noTerminator": false,
			"manualOffset": 0,
			"hasManualOffset": false
		},
		{
			"text_contents": "",
			"hasEntryInOffsetOffsets": true,
			"noTerminator": false,
			"manualOffset": 0,
			"hasManualOffset": false
		},
		{
			"text_contents": "はーっくしょいしょい！\nうっかり<18\u0000>道<19\u0000>みち<1:\u0000>に<18\u0000>迷<19\u0000>まよ<1:\u0000>っちまって<18\u0000>困<19\u0000>こま<1:\u0000>ってんだ。<1\"\u0000>\n<18\u0000>雨<19\u0000>あめ<1:\u0000>にも<18\u0000>降<19\u0000>ふ<1:\u0000>られちまうし……どうすっかなぁ。\nはーっくしょいしょい！",
			"hasEntryInOffsetOffsets": true,
			"noTerminator": false,
			"manualOffset": 0,
			"hasManualOffset": false
		},
		{
			"text_contents": "",
			"hasEntryInOffsetOffsets": true,
			"noTerminator": false,
			"manualOffset": 0,
			"hasManualOffset": false
		},
		{
			"text_contents": "<18\u0000>雨<19\u0000>あめ<1:\u0000>とピクニックとワタシ……\n<18\u0000>愛<19\u0000>あい<1:\u0000>するカレとふたりっきりでステキだわさ。<1\"\u0000>\n<18\u0000>独特<19\u0000>どくとく<1:\u0000>なくしゃみは<18\u0000>気<19\u0000>き<1:\u0000>になるけど\nそこもカレのカワイイところだわさ。",
			"hasEntryInOffsetOffsets": true,
			"noTerminator": false,
			"manualOffset": 0,
			"hasManualOffset": false
		},
		{
			"text_contents": "",
			"hasEntryInOffsetOffsets": true,
			"noTerminator": false,
			"manualOffset": 0,
			"hasManualOffset": false
		},
		{
			"text_contents": "ここが<17\u0003>{8, MessageNpcName, +}<2\u0001耀>{4, message}さんの<18\u0000>言<19\u0000>い<1:\u0000>ってた\n「<17\u0003>{8, MessageMapName, +}<24耀>{4, message}」みたいだね。<1\"\u0000>\nじゃあ、さっそく<18\u0000>落<19\u0000>おと<1:\u0000>し<18\u0000>物<19\u0000>もの<1:\u0000>を<18\u0000>探<19\u0000>さが<1:\u0000>そう！",
			"hasEntryInOffsetOffsets": true,
			"noTerminator": false,
			"manualOffset": 0,
			"hasManualOffset": false
		},
		{
			"text_contents": "몺⟦DEB6⟧␯敭獳条㩥敍獳条乥捰慎敭㈺㐱㐷㌸㐶㨹潶捩⑥⟦DDBB⟧⿉꾲⟃⿀洤獥慳敧䴺獥慳敧慍买浡㩥ㄲ㜴㠴㜳〰瘺楯散퀤쀧삲죞␮慰敧⼤⟦DEBC⟧➬粰꾻뢿딯별짓⾵뚻뿞딧.",
			"hasEntryInOffsetOffsets": true,
			"noTerminator": true,
			"manualOffset": 0,
			"hasManualOffset": false
		},
		{
			"text_contents": "ここが<17\u0003>{8, MessageNpcName, +}<2\u0001耀>{4, message}さんの<18\u0000>言<19\u0000>い<1:\u0000>ってた\n「<17\u0003>{8, MessageMapName, +}<24耀>{4, message}」みたいですね。<1\"\u0000>\nそれじゃあさっそく\n<18\u0000>落<19\u0000>おと<1:\u0000>し<18\u0000>物<19\u0000>もの<1:\u0000>を<18\u0000>探<19\u0000>さが<1:\u0000>しましょう！",
			"hasEntryInOffsetOffsets": true,
			"noTerminator": false,
			"manualOffset": 0,
			"hasManualOffset": false
		},
		{
			"text_contents": "몺⟦DEB6⟧␯敭獳条㩥敍獳条乥捰慎敭㈺㐱㐷㌸㐶㨹潶捩⑥⟦DDBB⟧⿉꾲⟃⿀洤獥慳敧䴺獥慳敧慍买浡㩥ㄲ㜴㠴㜳〰瘺楯散퀤쀧쎲뷞⻈瀤条⑥뼯볚곞뀧묯뾯⾸쒵펼뗉묯⟦DEB6⟧쾼꺼딧.",
			"hasEntryInOffsetOffsets": true,
			"noTerminator": true,
			"manualOffset": 0,
			"hasManualOffset": false
		},
		{
			"text_contents": "ここが<17\u0003>{8, MessageNpcName, +}<2\u0001耀>{4, message}さんの<18\u0000>言<19\u0000>い<1:\u0000>っていた\n「<17\u0003>{8, MessageMapName, +}<24耀>{4, message}」のようです。<1\"\u0000>\nそれではさっそく\n<18\u0000>落<19\u0000>おと<1:\u0000>し<18\u0000>物<19\u0000>もの<1:\u0000>を<18\u0000>探<19\u0000>さが<1:\u0000>しましょう。",
			"hasEntryInOffsetOffsets": true,
			"noTerminator": false,
			"manualOffset": 0,
			"hasManualOffset": false
		},
		{
			"text_contents": "몺⟦DEB6⟧␯敭獳条㩥敍獳条乥捰慎敭㈺㐱㐷㌸㐶㨹潶捩⑥⟦DDBB⟧⿉꾲닃⿀洤獥慳敧䴺獥慳敧慍买浡㩥ㄲ㜴㠴㜳〰瘺楯散줤⟖쎰뷞⸾瀤条⑥뼯쏚⟞⿜꾻뢿딯별짓⾵뚻볞볏➮⺵",
			"hasEntryInOffsetOffsets": true,
			"noTerminator": false,
			"manualOffset": 0,
			"hasManualOffset": false
		},
		{
			"text_contents": "<17\u0003>{8, MessageNpcName, +}<2\u0001耀>{4, message}さんが<18\u0000>言<19\u0000>い<1:\u0000>ってた\n「<17\u0003>{8, MessageMapName, +}<24耀>{4, message}」ってのはここか。<1\"\u0000>\nよし！<18\u0000>落<19\u0000>おと<1:\u0000>し<18\u0000>物探<19\u0000>ものさが<1:\u0000>すぜ！",
			"hasEntryInOffsetOffsets": true,
			"noTerminator": false,
			"manualOffset": 0,
			"hasManualOffset": false
		},
		{
			"text_contents": "洤獥慳敧䴺獥慳敧灎乣浡㩥ㄲ㜴㠴㘳㤴瘺楯散묤뛝⿞꾲⟃糀洤獥慳敧䴺獥慳敧慍买浡㩥ㄲ㜴㠴㜳〰瘺楯散꼤짃⿜몺Ⓐ慰敧혤밧ぼ쒵펼⿉뚻뷞븧⻞",
			"hasEntryInOffsetOffsets": true,
			"noTerminator": false,
			"manualOffset": 0,
			"hasManualOffset": false
		},
		{
			"text_contents": "ここだよね。\n<17\u0003>{8, MessageNpcName, +}<2\u0001耀>{4, message}さんの<18\u0000>言<19\u0000>い<1:\u0000>ってた「<17\u0003>{8, MessageMapName, +}<24耀>{4, message}」って。<1\"\u0000>\nそれじゃー<18\u0000>落<19\u0000>おと<1:\u0000>し<18\u0000>物<19\u0000>もの<1:\u0000>を<18\u0000>探<19\u0000>さが<1:\u0000>しにいこう！",
			"hasEntryInOffsetOffsets": true,
			"noTerminator": false,
			"manualOffset": 0,
			"hasManualOffset": false
		},
		{
			"text_contents": "몺⟦DEC0⟧혧⻈洤獥慳敧䴺獥慳敧灎乣浡㩥ㄲ㜴㠴㘳㤴瘺楯散묤짝눯쎯쀧␯敭獳条㩥敍獳条䵥灡慎敭㈺㐱㐷㌸〷㨰潶捩⑥쎯␮慰敧⼤⟦DABF⟧⟦DEBC⟧➬⾰쒵펼뗉묯⟦DEB6⟧욼눯➺⺵",
			"hasEntryInOffsetOffsets": true,
			"noTerminator": false,
			"manualOffset": 0,
			"hasManualOffset": false
		},
		{
			"text_contents": "ねえ、ここで<18\u0000>合<19\u0000>あ<1:\u0000>ってるわよね？\n「<17\u0003>{8, MessageMapName, +}<24耀>{4, message}」よね。<1\"\u0000>\nじゃあさっそく\n<18\u0000>落<19\u0000>おと<1:\u0000>し<18\u0000>物<19\u0000>もの<1:\u0000>を<18\u0000>探<19\u0000>さが<1:\u0000>すわよ！",
			"hasEntryInOffsetOffsets": true,
			"noTerminator": false,
			"manualOffset": 0,
			"hasManualOffset": false
		},
		{
			"text_contents": "냈멼쎺⿞➱쎯⟦DCD9⟧죖␿敭獳条㩥敍獳条䵥灡慎敭㈺㐱㐷㌸〷㨰潶捩⑥죖␮慰敧⼤⟦DEBC⟧➬⾰꾻뢿簧딲별짓⾵뚻뷞⟦DC27⟧⻖",
			"hasEntryInOffsetOffsets": true,
			"noTerminator": false,
			"manualOffset": 0,
			"hasManualOffset": false
		},
		{
			"text_contents": "ここかね。<18\u0000>彼<19\u0000>かれ<1:\u0000>が<18\u0000>言<19\u0000>い<1:\u0000>っていた\n「<17\u0003>{8, MessageMapName, +}<24耀>{4, message}」というのは。<1\"\u0000>\nでは、<18\u0000>落<19\u0000>おと<1:\u0000>し<18\u0000>物<19\u0000>もの<1:\u0000>を<18\u0000>探<19\u0000>さが<1:\u0000>しに<18\u0000>行<19\u0000>い<1:\u0000>こうではないか。",
			"hasEntryInOffsetOffsets": true,
			"noTerminator": false,
			"manualOffset": 0,
			"hasManualOffset": false
		},
		{
			"text_contents": "몺➶⻈➶뛚⿞꾲닃⿀洤獥慳敧䴺獥慳敧慍买浡㩥ㄲ㜴㠴㜳〰瘺楯散쐤눯➳⟦DCC9⟧␮慰敧쌤⟦DCDE⟧땼별짓⾵뚻볞⿆몲딧⟦DEC3⟧⿜⟅뚲.",
			"hasEntryInOffsetOffsets": true,
			"noTerminator": true,
			"manualOffset": 0,
			"hasManualOffset": false
		},
		{
			"text_contents": "ここですかねえ。<17\u0003>{8, MessageNpcName, +}<2\u0001耀>{4, message}さんが<18\u0000>言<19\u0000>い<1:\u0000>ってた\n「<17\u0003>{8, MessageMapName, +}<24耀>{4, message}」ってのは。<1\"\u0000>\n<18\u0000>落<19\u0000>おと<1:\u0000>し<18\u0000>物<19\u0000>もの<1:\u0000><18\u0000>探<19\u0000>さが<1:\u0000>しかー。\nまあ、<18\u0000>頑張<19\u0000>がんば<1:\u0000>りますよ。",
			"hasEntryInOffsetOffsets": true,
			"noTerminator": false,
			"manualOffset": 0,
			"hasManualOffset": false
		},
		{
			"text_contents": "몺⟦DEC3⟧봧똾냈␮敭獳条㩥敍獳条乥捰慎敭㈺㐱㐷㌸㐶㨹潶捩⑥⟦DDBB⟧⟦DEB6⟧눯쎯쀧␯敭獳条㩥敍獳条䵥灡慎敭㈺㐱㐷㌸〷㨰潶捩⑥쎯줾⟦DC27⟧瀤条⑥쒵펼⿉➻⟦DEB6⟧㺼낶켮뀧뙼⟦DDDE⟧⟦DECA⟧쿘봧⻖",
			"hasEntryInOffsetOffsets": true,
			"noTerminator": false,
			"manualOffset": 0,
			"hasManualOffset": false
		},
		{
			"text_contents": "「<17\u0003>{8, MessageMapName, +}<2\u000C耀>{4, message}」の<18\u0000>時<19\u0000>とき<1:\u0000>みたいに\nモンスターに<18\u0000>襲<19\u0000>おそ<1:\u0000>われないといいんだけど……。",
			"hasEntryInOffsetOffsets": true,
			"noTerminator": false,
			"manualOffset": 0,
			"hasManualOffset": false
		},
		{
			"text_contents": "洤獥慳敧䴺獥慳敧慍买浡㩥ㄲ㜴㠴㘳〶瘺楯散줤쐯➷샐욲㉼⟓뷝쀾우딯⟦DCBF⟧엚➲⿄늲⟦DD27⟧⟦DEC0⟧쒹⻞",
			"hasEntryInOffsetOffsets": true,
			"noTerminator": false,
			"manualOffset": 0,
			"hasManualOffset": false
		},
		{
			"text_contents": "「<17\u0003>{8, MessageMapName, +}<2\u000C耀>{4, message}」の<18\u0000>時<19\u0000>とき<1:\u0000>みたいに\nモンスターから<18\u0000>襲<19\u0000>おそ<1:\u0000>われないといいんですけど。",
			"hasEntryInOffsetOffsets": true,
			"noTerminator": false,
			"manualOffset": 0,
			"hasManualOffset": false
		},
		{
			"text_contents": "洤獥慳敧䴺獥慳敧慍买浡㩥ㄲ㜴㠴㘳〶瘺楯散줤럄퀧닀糆팲⟦DD27⟧㺽냀ힶ㉼뾵⟦DADC⟧닅쐧눯➲쏝뷞뤾⟦DEC4⟧.",
			"hasEntryInOffsetOffsets": true,
			"noTerminator": true,
			"manualOffset": 0,
			"hasManualOffset": false
		},
		{
			"text_contents": "「<17\u0003>{8, MessageMapName, +}<2\u000C耀>{4, message}」の<18\u0000>時<19\u0000>とき<1:\u0000>のように\nモンスターから<18\u0000>襲<19\u0000>おそ<1:\u0000>われないといいのですが。",
			"hasEntryInOffsetOffsets": true,
			"noTerminator": false,
			"manualOffset": 0,
			"hasManualOffset": false
		},
		{
			"text_contents": "洤獥慳敧䴺獥慳敧慍买浡㩥ㄲ㜴㠴㘳〶瘺楯散줤쐯➷훉우㉼⟓뷝쀾뚰⿗뾵⟦DADC⟧닅쐧눯➲쏉뷞⟦DEB6⟧.",
			"hasEntryInOffsetOffsets": true,
			"noTerminator": true,
			"manualOffset": 0,
			"hasManualOffset": false
		},
		{
			"text_contents": "「<17\u0003>{8, MessageMapName, +}<2\u000C耀>{4, message}」の<18\u0000>時<19\u0000>とき<1:\u0000>みたく\nモンスターに<18\u0000>襲<19\u0000>おそ<1:\u0000>われないよな？",
			"hasEntryInOffsetOffsets": true,
			"noTerminator": false,
			"manualOffset": 0,
			"hasManualOffset": false
		},
		{
			"text_contents": "洤獥慳敧䴺獥慳敧慍买浡㩥ㄲ㜴㠴㘳〶瘺楯散줤럄퀧룀㉼⟓뷝쀾우딯⟦DCBF⟧엚눧엖?",
			"hasEntryInOffsetOffsets": true,
			"noTerminator": true,
			"manualOffset": 0,
			"hasManualOffset": false
		},
		{
			"text_contents": "モンスターには<18\u0000>襲<19\u0000>おそ<1:\u0000>われないよね……？\n「<17\u0003>{8, MessageMapName, +}<2\u000C耀>{4, message}」の<18\u0000>時<19\u0000>とき<1:\u0000>みたいに。",
			"hasEntryInOffsetOffsets": true,
			"noTerminator": false,
			"manualOffset": 0,
			"hasManualOffset": false
		},
		{
			"text_contents": "⟓뷝쀾우⿜뾵⟦DADC⟧닅혧㿈洤獥慳敧䴺獥慳敧慍买浡㩥ㄲ㜴㠴㘳〶瘺楯散줤쐯➷샐욲.",
			"hasEntryInOffsetOffsets": true,
			"noTerminator": true,
			"manualOffset": 0,
			"hasManualOffset": false
		},
		{
			"text_contents": "「<17\u0003>{8, MessageMapName, +}<2\u000C耀>{4, message}」の<18\u0000>時<19\u0000>とき<1:\u0000>みたいに\nモンスターに<18\u0000>襲<19\u0000>おそ<1:\u0000>われ……ないわよね？<1\"\u0000>\nあらやだ……ちょっと<18\u0000>寒気<19\u0000>さむけ<1:\u0000>がするわ。",
			"hasEntryInOffsetOffsets": true,
			"noTerminator": false,
			"manualOffset": 0,
			"hasManualOffset": false
		},
		{
			"text_contents": "洤獥慳敧䴺獥慳敧慍买浡㩥ㄲ㜴㠴㘳〶瘺楯散줤쐯뜧샐욲㉼⟓뷝쀾우딯⟦DCBF⟧糚猷씷눧훜㿈瀤条⑥넯휧퐯쀧糞껁꼧⿄톻➹⟦DEB6⟧봯⿙⟦DC27⟧.",
			"hasEntryInOffsetOffsets": true,
			"noTerminator": true,
			"manualOffset": 0,
			"hasManualOffset": false
		},
		{
			"text_contents": "「<17\u0003>{8, MessageMapName, +}<2\u000C耀>{4, message}」の<18\u0000>時<19\u0000>とき<1:\u0000>のように\nモンスターから<18\u0000>襲<19\u0000>おそ<1:\u0000>われたりはしないだろな……。",
			"hasEntryInOffsetOffsets": true,
			"noTerminator": false,
			"manualOffset": 0,
			"hasManualOffset": false
		},
		{
			"text_contents": "洤獥慳敧䴺獥慳敧慍买浡㩥ㄲ㜴㠴㘳〶瘺楯散줤럄줧냖糆팲⟦DD27⟧㺽냀ힶ딯⟦DCBF⟧샚⟦D827⟧⿜얼눧⟦DEC0⟧엛.",
			"hasEntryInOffsetOffsets": true,
			"noTerminator": true,
			"manualOffset": 0,
			"hasManualOffset": false
		},
		{
			"text_contents": "「<17\u0003>{8, MessageMapName, +}<2\u000C耀>{4, message}」の<18\u0000>時<19\u0000>とき<1:\u0000>みたく\nモンスターに<18\u0000>襲<19\u0000>おそ<1:\u0000>われないですよねえ。やだなー。",
			"hasEntryInOffsetOffsets": true,
			"noTerminator": false,
			"manualOffset": 0,
			"hasManualOffset": false
		},
		{
			"text_contents": "洤獥慳敧䴺獥慳敧慍买浡㩥ㄲ㜴㠴㘳〶瘺楯散줤럄퀯⟀粸팲⟦DD27⟧㺽냀⿆뾵⟦DADC⟧⟅쎲뷞죖⺰⟔⟦DEC0⟧냅.",
			"hasEntryInOffsetOffsets": true,
			"noTerminator": true,
			"manualOffset": 0,
			"hasManualOffset": false
		},
		{
			"text_contents": "うーん、ぜんぜん<18\u0000>見<19\u0000>み<1:\u0000>つからないね。\nあとはこの<18\u0000>奥<19\u0000>おく<1:\u0000>ぐらいだと<18\u0000>思<19\u0000>おも<1:\u0000>うけど……。",
			"hasEntryInOffsetOffsets": true,
			"noTerminator": false,
			"manualOffset": 0,
			"hasManualOffset": false
		},
		{
			"text_contents": "낳糝⟦DEBE⟧뻝⟦DDDE⟧퀯㻂ힶ닅⻈➱⟦DCC4⟧먯⿉➵뢸ퟞ삲쓞딯⟓릳⟦DEC4⟧.",
			"hasEntryInOffsetOffsets": true,
			"noTerminator": true,
			"manualOffset": 0,
			"hasManualOffset": false
		},
		{
			"text_contents": "うーん、ぜんぜん<18\u0000>見<19\u0000>み<1:\u0000>つかりませんね。\nあとはこの<18\u0000>奥<19\u0000>おく<1:\u0000>ぐらいだと<18\u0000>思<19\u0000>おも<1:\u0000>いますが。",
			"hasEntryInOffsetOffsets": true,
			"noTerminator": false,
			"manualOffset": 0,
			"hasManualOffset": false
		},
		{
			"text_contents": "낳糝⟦DEBE⟧뻝⟦DDDE⟧퀯㻂⟦D8B6⟧뻏⟦DD27⟧⻈➱⟦DCC4⟧먯⿉➵뢸ퟞ삲쓞딯닓⟏뚽⻞",
			"hasEntryInOffsetOffsets": true,
			"noTerminator": false,
			"manualOffset": 0,
			"hasManualOffset": false
		},
		{
			"text_contents": "ふむ、なぜでしょう。まったく<18\u0000>見<19\u0000>み<1:\u0000>つかりません。\nあとはこの<18\u0000>奥<19\u0000>おく<1:\u0000>ぐらいなのですが……。",
			"hasEntryInOffsetOffsets": true,
			"noTerminator": false,
			"manualOffset": 0,
			"hasManualOffset": false
		},
		{
			"text_contents": "퇌야븧쏞볞떮켮삯⾸싐똾쿘➾⻝➱⟦DCC4⟧먯⿉➵뢸ퟞ얲쏉뷞⟦DEB6⟧.",
			"hasEntryInOffsetOffsets": true,
			"noTerminator": true,
			"manualOffset": 0,
			"hasManualOffset": false
		},
		{
			"text_contents": "う゛ーん……ぜーんぜん<18\u0000>見<19\u0000>み<1:\u0000>つからねー。\nあとはこの<18\u0000>奥<19\u0000>おく<1:\u0000>ぐらいか……。",
			"hasEntryInOffsetOffsets": true,
			"noTerminator": false,
			"manualOffset": 0,
			"hasManualOffset": false
		},
		{
			"text_contents": "낳糝⟦DEBE⟧⟦DDB0⟧⟦DEBE⟧⿝싐똾죗⺰➱⟦DCC4⟧먯⿉➵⾸⟦DEB8⟧닗⺶",
			"hasEntryInOffsetOffsets": true,
			"noTerminator": false,
			"manualOffset": 0,
			"hasManualOffset": false
		},
		{
			"text_contents": "うーん、ぜんぜん<18\u0000>見<19\u0000>み<1:\u0000>つからないよ。\nあとはこの<18\u0000>奥<19\u0000>おく<1:\u0000>ぐらいだよねー……。",
			"hasEntryInOffsetOffsets": true,
			"noTerminator": false,
			"manualOffset": 0,
			"hasManualOffset": false
		},
		{
			"text_contents": "낳糝⟦DEBE⟧뻝⟦DDDE⟧퀯㻂ힶ닅혧넮쐧⿜즺딯렧⟦DEB8⟧닗⟦DEC0⟧죖⺰",
			"hasEntryInOffsetOffsets": true,
			"noTerminator": false,
			"manualOffset": 0,
			"hasManualOffset": false
		},
		{
			"text_contents": "ねえ、ぜんぜん<18\u0000>見<19\u0000>み<1:\u0000>つからないわ。\nあと<18\u0000>探<19\u0000>さが<1:\u0000>すならこの<18\u0000>奥<19\u0000>おく<1:\u0000>ぐらい、よね？",
			"hasEntryInOffsetOffsets": true,
			"noTerminator": false,
			"manualOffset": 0,
			"hasManualOffset": false
		},
		{
			"text_contents": "냈빼⟦DDDE⟧⟦DEBE⟧⿝싐똾엗➲⻜➱⿄뚻뷞⟅⿗즺뢵⟦DEB8⟧휧⾲죖?",
			"hasEntryInOffsetOffsets": true,
			"noTerminator": true,
			"manualOffset": 0,
			"hasManualOffset": false
		},
		{
			"text_contents": "まったく、<18\u0000>見<19\u0000>み<1:\u0000>つからないではないか。\nこの<18\u0000>奥<19\u0000>おく<1:\u0000>がまだだが……。",
			"hasEntryInOffsetOffsets": true,
			"noTerminator": false,
			"manualOffset": 0,
			"hasManualOffset": false
		},
		{
			"text_contents": "꿏룀퀯㻂ힶ닅⟦DEC3⟧⟦DC27⟧씯눧⺶즺딯렧⟦DEB6⟧켯쀧샞뛞⻞",
			"hasEntryInOffsetOffsets": true,
			"noTerminator": false,
			"manualOffset": 0,
			"hasManualOffset": false
		},
		{
			"text_contents": "ぜんぜん<18\u0000>見<19\u0000>み<1:\u0000>つかりませんよ……はあ。\nまあ、この<18\u0000>奥<19\u0000>おく<1:\u0000>まだ<18\u0000>探<19\u0000>さが<1:\u0000>してませんが。",
			"hasEntryInOffsetOffsets": true,
			"noTerminator": false,
			"manualOffset": 0,
			"hasManualOffset": false
		},
		{
			"text_contents": "⟦DEBE⟧뻝⟦DDDE⟧퀯㻂⟦D8B6⟧뻏⟦DD27⟧糖㥳⟊粰猸켹뀧ぼ㕳즺딯렧켯쀧⿞뚻볞쌾뻏⟦DD27⟧⟦DEB6⟧.",
			"hasEntryInOffsetOffsets": true,
			"noTerminator": true,
			"manualOffset": 0,
			"hasManualOffset": false
		},
		{
			"text_contents": "<18\u0000>嫌<19\u0000>いや<1:\u0000>な<18\u0000>予感<19\u0000>よかん<1:\u0000>がするなぁ……。",
			"hasEntryInOffsetOffsets": true,
			"noTerminator": false,
			"manualOffset": 0,
			"hasManualOffset": false
		},
		{
			"text_contents": "풲씧혯⟦DDB6⟧⟦DEB6⟧봯⟦D92F⟧⟅⺰",
			"hasEntryInOffsetOffsets": true,
			"noTerminator": false,
			"manualOffset": 0,
			"hasManualOffset": false
		},
		{
			"text_contents": "<18\u0000>嫌<19\u0000>いや<1:\u0000>な<18\u0000>予感<19\u0000>よかん<1:\u0000>がします……。",
			"hasEntryInOffsetOffsets": true,
			"noTerminator": false,
			"manualOffset": 0,
			"hasManualOffset": false
		},
		{
			"text_contents": "풲씧혯⟦DDB6⟧⟦DEB6⟧밯⟏㺽.",
			"hasEntryInOffsetOffsets": true,
			"noTerminator": true,
			"manualOffset": 0,
			"hasManualOffset": false
		},
		{
			"text_contents": "<18\u0000>私<19\u0000>わたし<1:\u0000>のカンが<18\u0000>行<19\u0000>い<1:\u0000>くなと<18\u0000>囁<19\u0000>ささや<1:\u0000>いて……\nいえ、<18\u0000>何<19\u0000>なん<1:\u0000>でもないです。",
			"hasEntryInOffsetOffsets": true,
			"noTerminator": false,
			"manualOffset": 0,
			"hasManualOffset": false
		},
		{
			"text_contents": "샜즼똯⟝⟦DEB6⟧눯➸쓅묯풻눧糃뒲야쏝폞⟅쎲뷞⸾",
			"hasEntryInOffsetOffsets": true,
			"noTerminator": false,
			"manualOffset": 0,
			"hasManualOffset": false
		},
		{
			"text_contents": "なーんか<18\u0000>嫌<19\u0000>いや<1:\u0000>な<18\u0000>予感<19\u0000>よかん<1:\u0000>が……\nうおっ！？<18\u0000>今<19\u0000>いま<1:\u0000>なんか<18\u0000>寒気<19\u0000>さむけ<1:\u0000>がした！",
			"hasEntryInOffsetOffsets": true,
			"noTerminator": false,
			"manualOffset": 0,
			"hasManualOffset": false
		},
		{
			"text_contents": "냅⟦DD27⟧⾶풲씧혯⟦DDB6⟧⟦DEB6⟧㡼떳꼧눿켧씯⟝粶톻➹⟦DEB6⟧밯쀾.",
			"hasEntryInOffsetOffsets": true,
			"noTerminator": true,
			"manualOffset": 0,
			"hasManualOffset": false
		},
		{
			"text_contents": "なんだか<18\u0000>嫌<19\u0000>いや<1:\u0000>な<18\u0000>予感<19\u0000>よかん<1:\u0000>しかしないよ……。",
			"hasEntryInOffsetOffsets": true,
			"noTerminator": false,
			"manualOffset": 0,
			"hasManualOffset": false
		},
		{
			"text_contents": "⟅생뛞눯⟔⿅뛖볝✾⾶얼눧⻖",
			"hasEntryInOffsetOffsets": true,
			"noTerminator": false,
			"manualOffset": 0,
			"hasManualOffset": false
		},
		{
			"text_contents": "なんだか……<18\u0000>嫌<19\u0000>いや<1:\u0000>な<18\u0000>予感<19\u0000>よかん<1:\u0000>がするのよ。\nキャッ！やだーなんだか<18\u0000>寒気<19\u0000>さむけ<1:\u0000>がするわ。",
			"hasEntryInOffsetOffsets": true,
			"noTerminator": false,
			"manualOffset": 0,
			"hasManualOffset": false
		},
		{
			"text_contents": "⟅생뛞뉼⟔⿅뛖뛝⿞⟦D9BD⟧줧⻖겷꼧푼쀧냞㉼⟅생뛞묯맑똧⿞⟦D9BD⟧⟦DC27⟧.",
			"hasEntryInOffsetOffsets": true,
			"noTerminator": true,
			"manualOffset": 0,
			"hasManualOffset": false
		},
		{
			"text_contents": "……<18\u0000>君<19\u0000>きみ<1:\u0000>、<18\u0000>先<19\u0000>さき<1:\u0000>へ<18\u0000>行<19\u0000>い<1:\u0000>ってもよいのだぞ。",
			"hasEntryInOffsetOffsets": true,
			"noTerminator": false,
			"manualOffset": 0,
			"hasManualOffset": false
		},
		{
			"text_contents": "킷뭼뒷눯쎯팧혯눧색뿞⻞",
			"hasEntryInOffsetOffsets": true,
			"noTerminator": false,
			"manualOffset": 0,
			"hasManualOffset": false
		},
		{
			"text_contents": "<18\u0000>行<19\u0000>い<1:\u0000>くしかないんですよね……はあ。",
			"hasEntryInOffsetOffsets": true,
			"noTerminator": false,
			"manualOffset": 0,
			"hasManualOffset": false
		},
		{
			"text_contents": "뢲밾✾⾶⟅⟦DDB2⟧⟦DEC3⟧횽糈⟊⺰",
			"hasEntryInOffsetOffsets": true,
			"noTerminator": false,
			"manualOffset": 0,
			"hasManualOffset": false
		},
		{
			"text_contents": "……<18\u0000>何者<19\u0000>なにもの<1:\u0000>ケロ。",
			"hasEntryInOffsetOffsets": true,
			"noTerminator": false,
			"manualOffset": 0,
			"hasManualOffset": false
		},
		{
			"text_contents": "",
			"hasEntryInOffsetOffsets": true,
			"noTerminator": false,
			"manualOffset": 0,
			"hasManualOffset": false
		},
		{
			"text_contents": "あっ、こんにちは。",
			"hasEntryInOffsetOffsets": true,
			"noTerminator": false,
			"manualOffset": 0,
			"hasManualOffset": false
		},
		{
			"text_contents": "꾱멼웝⟦DCC1⟧.",
			"hasEntryInOffsetOffsets": true,
			"noTerminator": true,
			"manualOffset": 0,
			"hasManualOffset": false
		},
		{
			"text_contents": "あっ、はじめまして。",
			"hasEntryInOffsetOffsets": true,
			"noTerminator": false,
			"manualOffset": 0,
			"hasManualOffset": false
		},
		{
			"text_contents": "꾱쩼⟦DEBC⟧쿒밧쌾.",
			"hasEntryInOffsetOffsets": true,
			"noTerminator": true,
			"manualOffset": 0,
			"hasManualOffset": false
		},
		{
			"text_contents": "これは、<18\u0000>先客<19\u0000>せんきゃく<1:\u0000>がいましたか。",
			"hasEntryInOffsetOffsets": true,
			"noTerminator": false,
			"manualOffset": 0,
			"hasManualOffset": false
		},
		{
			"text_contents": "⟦DABA⟧糜⟦DDBE⟧겷뚸⿞쾲밧쀾⺶",
			"hasEntryInOffsetOffsets": true,
			"noTerminator": false,
			"manualOffset": 0,
			"hasManualOffset": false
		},
		{
			"text_contents": "お？<18\u0000>何<19\u0000>なん<1:\u0000>だって<18\u0000>何<19\u0000>なん<1:\u0000>だ？",
			"hasEntryInOffsetOffsets": true,
			"noTerminator": false,
			"manualOffset": 0,
			"hasManualOffset": false
		},
		{
			"text_contents": "㾵⟅생꿞⿃⟅생㿞",
			"hasEntryInOffsetOffsets": true,
			"noTerminator": false,
			"manualOffset": 0,
			"hasManualOffset": false
		},
		{
			"text_contents": "こんにちはー。",
			"hasEntryInOffsetOffsets": true,
			"noTerminator": false,
			"manualOffset": 0,
			"hasManualOffset": false
		},
		{
			"text_contents": "⟦DDBA⟧쇆⟦DC3E⟧⺰",
			"hasEntryInOffsetOffsets": true,
			"noTerminator": false,
			"manualOffset": 0,
			"hasManualOffset": false
		},
		{
			"text_contents": "あら、こんにちは。",
			"hasEntryInOffsetOffsets": true,
			"noTerminator": false,
			"manualOffset": 0,
			"hasManualOffset": false
		},
		{
			"text_contents": "ힱ멼웝⟦DCC1⟧.",
			"hasEntryInOffsetOffsets": true,
			"noTerminator": true,
			"manualOffset": 0,
			"hasManualOffset": false
		},
		{
			"text_contents": "おお、ちょうどいい。",
			"hasEntryInOffsetOffsets": true,
			"noTerminator": false,
			"manualOffset": 0,
			"hasManualOffset": false
		},
		{
			"text_contents": "➵粰껁쒰닞뀧.",
			"hasEntryInOffsetOffsets": true,
			"noTerminator": true,
			"manualOffset": 0,
			"hasManualOffset": false
		},
		{
			"text_contents": "あ、ども……。",
			"hasEntryInOffsetOffsets": true,
			"noTerminator": false,
			"manualOffset": 0,
			"hasManualOffset": false
		},
		{
			"text_contents": "粱⟦DEC4⟧⻓",
			"hasEntryInOffsetOffsets": true,
			"noTerminator": false,
			"manualOffset": 0,
			"hasManualOffset": false
		},
		{
			"text_contents": "<18\u0000>実<19\u0000>じつ<1:\u0000>はボク、<18\u0000>探<19\u0000>さが<1:\u0000>し<18\u0000>物<19\u0000>もの<1:\u0000>をしてるんだけど\nここらへんで<18\u0000>落<19\u0000>おと<1:\u0000>し<18\u0000>物<19\u0000>もの<1:\u0000>を<18\u0000>見<19\u0000>み<1:\u0000>なかった？",
			"hasEntryInOffsetOffsets": true,
			"noTerminator": false,
			"manualOffset": 0,
			"hasManualOffset": false
		},
		{
			"text_contents": "⟦DEBC⟧⟂⿜⟦DECE⟧렧ぼ뚻볞팾뗉밯쌾⟦D927⟧⟦DD27⟧⟦DEC0⟧쒹糞몺췗쏝糞따별짓⾵⟐뛅삯?",
			"hasEntryInOffsetOffsets": true,
			"noTerminator": true,
			"manualOffset": 0,
			"hasManualOffset": false
		},
		{
			"text_contents": "<18\u0000>実<19\u0000>じつ<1:\u0000>は<18\u0000>私<19\u0000>わたし<1:\u0000>、<18\u0000>探<19\u0000>さが<1:\u0000>し<18\u0000>物<19\u0000>もの<1:\u0000>をしているのですが\nこのあたりで<18\u0000>落<19\u0000>おと<1:\u0000>し<18\u0000>物<19\u0000>もの<1:\u0000>を<18\u0000>見<19\u0000>み<1:\u0000>ませんでしたか？",
			"hasEntryInOffsetOffsets": true,
			"noTerminator": false,
			"manualOffset": 0,
			"hasManualOffset": false
		},
		{
			"text_contents": "⟦DEBC⟧⟂⿜샜粼뚻볞팾뗉밯쌾➲짙쌯뷞⟦DEB6⟧멼⿉삱⟘⟦DEC3⟧ぼ쒵펼뗉퀯뻏⟦DD27⟧⟦DEC3⟧㺼뛀?",
			"hasEntryInOffsetOffsets": true,
			"noTerminator": true,
			"manualOffset": 0,
			"hasManualOffset": false
		},
		{
			"text_contents": "<18\u0000>恐<19\u0000>おそ<1:\u0000>れ<18\u0000>入<19\u0000>い<1:\u0000>ります。<18\u0000>落<19\u0000>おと<1:\u0000>し<18\u0000>物<19\u0000>もの<1:\u0000>を<18\u0000>探<19\u0000>さが<1:\u0000>していまして\nこの<18\u0000>辺<19\u0000>あた<1:\u0000>りにそれらしき<18\u0000>物<19\u0000>もの<1:\u0000>が<18\u0000>落<19\u0000>お<1:\u0000>ちては……。",
			"hasEntryInOffsetOffsets": true,
			"noTerminator": false,
			"manualOffset": 0,
			"hasManualOffset": false
		},
		{
			"text_contents": "뾵⟦DA27⟧눯쿘봧⸾쒵펼뗉묯⟦DEB6⟧㺼닃⟏㺼糃먲뇉쀧웘뼯ퟚ밧뜾팯⟉⟦DEB6⟧딯섧쌾⻜",
			"hasEntryInOffsetOffsets": true,
			"noTerminator": false,
			"manualOffset": 0,
			"hasManualOffset": false
		},
		{
			"text_contents": "まあいいや！\nこのへんで<18\u0000>落<19\u0000>おと<1:\u0000>し<18\u0000>物<19\u0000>もの<1:\u0000>っぽいの<18\u0000>見<19\u0000>み<1:\u0000>てないか？",
			"hasEntryInOffsetOffsets": true,
			"noTerminator": false,
			"manualOffset": 0,
			"hasManualOffset": false
		},
		{
			"text_contents": "⟏⾰➲풰멼췉쏝⿞쒵펼꿉⟦DFCE⟧눧⿉⟐엃뚲?",
			"hasEntryInOffsetOffsets": true,
			"noTerminator": true,
			"manualOffset": 0,
			"hasManualOffset": false
		},
		{
			"text_contents": "<18\u0000>僕<19\u0000>ぼく<1:\u0000>、<18\u0000>探<19\u0000>さが<1:\u0000>し<18\u0000>物<19\u0000>もの<1:\u0000>をしてるんだ。\nここで<18\u0000>落<19\u0000>おと<1:\u0000>し<18\u0000>物<19\u0000>もの<1:\u0000>を<18\u0000>見<19\u0000>み<1:\u0000>なかった？",
			"hasEntryInOffsetOffsets": true,
			"noTerminator": false,
			"manualOffset": 0,
			"hasManualOffset": false
		},
		{
			"text_contents": "⟦DECE⟧렧뭼⟦DEB6⟧펼뗉밯쌾⟙생⻞몺⟦DEC3⟧딯별짓⾵⟐뛅삯?",
			"hasEntryInOffsetOffsets": true,
			"noTerminator": true,
			"manualOffset": 0,
			"hasManualOffset": false
		},
		{
			"text_contents": "ねえ、あなた。アタシ<18\u0000>探<19\u0000>さが<1:\u0000>し<18\u0000>物<19\u0000>もの<1:\u0000>してるの。\nこのへんで<18\u0000>落<19\u0000>おと<1:\u0000>し<18\u0000>物<19\u0000>もの<1:\u0000>なんてなかったかしら？",
			"hasEntryInOffsetOffsets": true,
			"noTerminator": false,
			"manualOffset": 0,
			"hasManualOffset": false
		},
		{
			"text_contents": "냈논⟅⻀삱➼묯⟦DEB6⟧펼⿉㺼⟦D9C3⟧줧먮췉쏝⟞딯별짓⟅쏝씯똧삯벶㿗",
			"hasEntryInOffsetOffsets": true,
			"noTerminator": false,
			"manualOffset": 0,
			"hasManualOffset": false
		},
		{
			"text_contents": "この<18\u0000>辺<19\u0000>あた<1:\u0000>りで<18\u0000>落<19\u0000>おと<1:\u0000>し<18\u0000>物<19\u0000>もの<1:\u0000>を<18\u0000>見<19\u0000>み<1:\u0000>なかったかね。\n<18\u0000>私<19\u0000>わたし<1:\u0000>は<18\u0000>探<19\u0000>さが<1:\u0000>し<18\u0000>物<19\u0000>もの<1:\u0000>をしているのだよ。",
			"hasEntryInOffsetOffsets": true,
			"noTerminator": false,
			"manualOffset": 0,
			"hasManualOffset": false
		},
		{
			"text_contents": "즺➱⟦D8C0⟧⟦DEC3⟧딯별짓⾵⟐뛅삯좶⟦DC2E⟧변⿜뚻볞짓➵밯쌾⟦D9B2⟧줧⟦DEC0⟧⻖",
			"hasEntryInOffsetOffsets": true,
			"noTerminator": false,
			"manualOffset": 0,
			"hasManualOffset": false
		},
		{
			"text_contents": "あのー……このへんに<18\u0000>何<19\u0000>なに<1:\u0000>か<18\u0000>落<19\u0000>お<1:\u0000>ちてませんでした？\nちょっと<18\u0000>探<19\u0000>さが<1:\u0000>しものをしていて……。",
			"hasEntryInOffsetOffsets": true,
			"noTerminator": false,
			"manualOffset": 0,
			"hasManualOffset": false
		},
		{
			"text_contents": "즱뀧멼췉⟝⿆⟅뛆딯섧쌾뻏쏝볞쀾섿➮쒯묯⟦DEB6⟧펼⟉⾵㺼닃쌧.",
			"hasEntryInOffsetOffsets": true,
			"noTerminator": true,
			"manualOffset": 0,
			"hasManualOffset": false
		},
		{
			"text_contents": "<18\u0000>探<19\u0000>さが<1:\u0000>し<18\u0000>物<19\u0000>もの<1:\u0000>……？ケロッ！？<1\"\u0000>\n<18\u0000>貴様<19\u0000>きさま<1:\u0000>「オーブ」を<18\u0000>奪<19\u0000>うば<1:\u0000>いに<18\u0000>来<19\u0000>き<1:\u0000>たケロな！！\nアレは<18\u0000>魔女様<19\u0000>まじょさま<1:\u0000>に<18\u0000>捧<19\u0000>ささ<1:\u0000>げたケロ！",
			"hasEntryInOffsetOffsets": true,
			"noTerminator": false,
			"manualOffset": 0,
			"hasManualOffset": false
		},
		{
			"text_contents": "",
			"hasEntryInOffsetOffsets": true,
			"noTerminator": false,
			"manualOffset": 0,
			"hasManualOffset": false
		},
		{
			"text_contents": "「オーブ」って<18\u0000>何<19\u0000>なん<1:\u0000>のこと？\nま、<18\u0000>魔女<19\u0000>まじょ<1:\u0000>ってだれ？<1\"\u0000>\nボ、ボクは<18\u0000>本当<19\u0000>ほんとう<1:\u0000>に\n<18\u0000>探<19\u0000>さが<1:\u0000>し<18\u0000>物<19\u0000>もの<1:\u0000>をしてるだけだよ！",
			"hasEntryInOffsetOffsets": true,
			"noTerminator": false,
			"manualOffset": 0,
			"hasManualOffset": false
		},
		{
			"text_contents": "➵첰꿞糃씲⟦DD27⟧뫉㿄糏켲밧껞쎯ぼ⟦DEC0⟧⟦DA27⟧␿慰敧츤糞⟦DECE⟧렧⿜⟦DDCE⟧냄⿆뚻볞짓➵밯쌾샙맞쀧훞.",
			"hasEntryInOffsetOffsets": true,
			"noTerminator": true,
			"manualOffset": 0,
			"hasManualOffset": false
		},
		{
			"text_contents": "「オーブ」って<18\u0000>何<19\u0000>なん<1:\u0000>のことですか？\nそれに<18\u0000>魔女<19\u0000>まじょ<1:\u0000>ってだれのことを<18\u0000>言<19\u0000>い<1:\u0000>って……。<1\"\u0000>\n<18\u0000>私<19\u0000>わたし<1:\u0000>は<18\u0000>本当<19\u0000>ほんとう<1:\u0000>に\n<18\u0000>探<19\u0000>さが<1:\u0000>し<18\u0000>物<19\u0000>もの<1:\u0000>をしてるだけですよ！",
			"hasEntryInOffsetOffsets": true,
			"noTerminator": false,
			"manualOffset": 0,
			"hasManualOffset": false
		},
		{
			"text_contents": "➵첰꿞⿃⟅짝쒺⟦DEC3⟧㺽㾶⟦DABF⟧⿆⟏⟦DEBC⟧꾮⿃⟦DEC0⟧⟦DA27⟧뫉뗄㌯꾲⻃瀤条⑥⟦DC2F⟧변⿜⟦DDCE⟧냄⿆뚻볞짓➵밯쌾샙맞쌧뷞⻖",
			"hasEntryInOffsetOffsets": true,
			"noTerminator": false,
			"manualOffset": 0,
			"hasManualOffset": false
		},
		{
			"text_contents": "「オーブ」とは……<18\u0000>何<19\u0000>なん<1:\u0000>ですか？\nそれに<18\u0000>魔女<19\u0000>まじょ<1:\u0000>という<18\u0000>方<19\u0000>かた<1:\u0000>も<18\u0000>存<19\u0000>ぞん<1:\u0000>じないのですが。<1\"\u0000>\n<18\u0000>私<19\u0000>わたし<1:\u0000>は<18\u0000>本当<19\u0000>ほんとう<1:\u0000>に\n<18\u0000>探<19\u0000>さが<1:\u0000>し<18\u0000>物<19\u0000>もの<1:\u0000>をしているだけでして……。",
			"hasEntryInOffsetOffsets": true,
			"noTerminator": false,
			"manualOffset": 0,
			"hasManualOffset": false
		},
		{
			"text_contents": "➵첰쓞糜씰⟦DD27⟧⟦DEC3⟧㺽㾶⟦DABF⟧⿆⟏⟦DEBC⟧쒮눯뚳⟀⿓⟦DEBF⟧볝엞➲쏉뷞⟦DEB6⟧␮慰敧⼤샜⟦DCBC⟧츯쓝우묯⟦DEB6⟧펼뗉⼧㺼닃샙맞쌧볞쌾.",
			"hasEntryInOffsetOffsets": true,
			"noTerminator": true,
			"manualOffset": 0,
			"hasManualOffset": false
		},
		{
			"text_contents": "「オーブ」？<18\u0000>魔女<19\u0000>まじょ<1:\u0000>ー？\n<18\u0000>何<19\u0000>なん<1:\u0000>だそりゃ？<1\"\u0000>\n<18\u0000>俺<19\u0000>おれ<1:\u0000>はただ<18\u0000>探<19\u0000>さが<1:\u0000>し<18\u0000>物<19\u0000>もの<1:\u0000>してるつってるだろ！！",
			"hasEntryInOffsetOffsets": true,
			"noTerminator": false,
			"manualOffset": 0,
			"hasManualOffset": false
		},
		{
			"text_contents": "➵첰㿞⟏⟦DEBC⟧떮簿⟦DDC5⟧⟦DEC0⟧뼧곘␿慰敧⼤⟦DAB5⟧⿜⟀⟦DEC0⟧뭼⟦DEB6⟧펼⟉밯쌾꿙⟂쎯⟦D927⟧⟦DEC0⟧⻛",
			"hasEntryInOffsetOffsets": true,
			"noTerminator": false,
			"manualOffset": 0,
			"hasManualOffset": false
		},
		{
			"text_contents": "「オーブ」って<18\u0000>何<19\u0000>なに<1:\u0000>？\n<18\u0000>魔女<19\u0000>まじょ<1:\u0000>さんて<18\u0000>人<19\u0000>ひと<1:\u0000>も<18\u0000>誰<19\u0000>だれ<1:\u0000>なのー？<1\"\u0000>\n<18\u0000>僕<19\u0000>ぼく<1:\u0000>、<18\u0000>本当<19\u0000>ほんとう<1:\u0000>に<18\u0000>探<19\u0000>さが<1:\u0000>し<18\u0000>物<19\u0000>もの<1:\u0000>してるだけだよ。",
			"hasEntryInOffsetOffsets": true,
			"noTerminator": false,
			"manualOffset": 0,
			"hasManualOffset": false
		},
		{
			"text_contents": "➵첰꿞⿃⟅㿆⟏⟦DEBC⟧뮮쏝쬯쐾팧쀯⟞엚냉␿慰敧⼤⟦DECE⟧렧칼쓝우묯⟦DEB6⟧펼⿉㺼⟦D9C3⟧⼧⟦DEC0⟧➹⟦DEC0⟧⻖",
			"hasEntryInOffsetOffsets": true,
			"noTerminator": false,
			"manualOffset": 0,
			"hasManualOffset": false
		},
		{
			"text_contents": "「オーブ」とか<18\u0000>魔女<19\u0000>まじょ<1:\u0000>とか<18\u0000>言<19\u0000>い<1:\u0000>われても\nさっぱりなんだけど……。<1\"\u0000>\n<18\u0000>探<19\u0000>さが<1:\u0000>し<18\u0000>物見<19\u0000>ものみ<1:\u0000>たわけじゃないなら\nアタシ<18\u0000>行<19\u0000>い<1:\u0000>くから。",
			"hasEntryInOffsetOffsets": true,
			"noTerminator": false,
			"manualOffset": 0,
			"hasManualOffset": false
		},
		{
			"text_contents": "➵첰쓞⾶⟏⟦DEBC⟧쒮⾶⟦DCB2⟧쏚팧묯쪯⟟엘생맞⟦DEC4⟧␮慰敧✤뚻볞짓퀯쀧맜⟦DEBC⟧⾬⟅얲糗넲변눯➸똾⻗",
			"hasEntryInOffsetOffsets": true,
			"noTerminator": false,
			"manualOffset": 0,
			"hasManualOffset": false
		},
		{
			"text_contents": "オーブンだか<18\u0000>孫<19\u0000>まご<1:\u0000>だか<18\u0000>知<19\u0000>し<1:\u0000>らぬが\nちゃんと<18\u0000>話<19\u0000>はなし<1:\u0000>を<18\u0000>聞<19\u0000>き<1:\u0000>かないか。<1\"\u0000>\n<18\u0000>私<19\u0000>わたし<1:\u0000>は<18\u0000>探<19\u0000>さが<1:\u0000>し<18\u0000>物<19\u0000>もの<1:\u0000>をしているだけだと\n<18\u0000>言<19\u0000>い<1:\u0000>っておるではないか。",
			"hasEntryInOffsetOffsets": true,
			"noTerminator": false,
			"manualOffset": 0,
			"hasManualOffset": false
		},
		{
			"text_contents": "➵첰⟦DDDE⟧⟦DEC0⟧⾶뫏⟞⟦DEC0⟧⾶ힼ⟇⟦DEB6⟧㉼곁쓝쨯⟅떼뜯똾⟅뚲␮慰敧⼤샜⟦DCBC⟧묯⟦DEB6⟧펼뗉밯쌾⟦D9B2⟧⟦DEC0⟧➹⟦DEC0⟧⿄꾲뗃⟦D927⟧⟦DEC3⟧⿜닅⺶",
			"hasEntryInOffsetOffsets": true,
			"noTerminator": false,
			"manualOffset": 0,
			"hasManualOffset": false
		},
		{
			"text_contents": "「オーブ」？<18\u0000>魔女<19\u0000>まじょ<1:\u0000>？\n……<18\u0000>何<19\u0000>なん<1:\u0000>ですかそれ。<1\"\u0000>\n<18\u0000>探<19\u0000>さが<1:\u0000>し<18\u0000>物<19\u0000>もの<1:\u0000>してるだけですって、こっちは……。",
			"hasEntryInOffsetOffsets": true,
			"noTerminator": false,
			"manualOffset": 0,
			"hasManualOffset": false
		},
		{
			"text_contents": "➵첰㿞⟏⟦DEBC⟧떮씿⟦DD27⟧⟦DEC3⟧㺽똯뼯⻚瀤条⑥묧⟦DEB6⟧펼⟉밯쌾⿙⟦DEC0⟧➹⟦DEC3⟧꾽⿃꾺⟁⻜",
			"hasEntryInOffsetOffsets": true,
			"noTerminator": false,
			"manualOffset": 0,
			"hasManualOffset": false
		},
		{
			"text_contents": "ぐぬぬっ……\nとぼけ<18\u0000>方<19\u0000>かた<1:\u0000>がますます<18\u0000>怪<19\u0000>あや<1:\u0000>しいケロ。<1\"\u0000>\n<18\u0000>貴様<19\u0000>きさま<1:\u0000>はここでヤッつけるケロ！！",
			"hasEntryInOffsetOffsets": true,
			"noTerminator": false,
			"manualOffset": 0,
			"hasManualOffset": false
		},
		{
			"text_contents": "",
			"hasEntryInOffsetOffsets": true,
			"noTerminator": false,
			"manualOffset": 0,
			"hasManualOffset": false
		},
		{
			"text_contents": "ケ、ケロー！？<18\u0000>頭<19\u0000>あたま<1:\u0000>が<18\u0000>痛<19\u0000>いた<1:\u0000>……。<1\"\u0000>\n……ケロ？……お<18\u0000>前<19\u0000>まえ<1:\u0000>、<18\u0000>誰<19\u0000>だれ<1:\u0000>ケロ。",
			"hasEntryInOffsetOffsets": true,
			"noTerminator": false,
			"manualOffset": 0,
			"hasManualOffset": false
		},
		{
			"text_contents": "",
			"hasEntryInOffsetOffsets": true,
			"noTerminator": false,
			"manualOffset": 0,
			"hasManualOffset": false
		},
		{
			"text_contents": "<18\u0000>急<19\u0000>きゅう<1:\u0000>に<18\u0000>何<19\u0000>なに<1:\u0000><18\u0000>言<19\u0000>い<1:\u0000>ってるの！？<1\"\u0000>\n<18\u0000>君<19\u0000>きみ<1:\u0000>が<18\u0000>人<19\u0000>ひと<1:\u0000>の<18\u0000>話<19\u0000>はなし<1:\u0000>を<18\u0000>聞<19\u0000>き<1:\u0000>かないで\n<18\u0000>襲<19\u0000>おそ<1:\u0000>いかかって<18\u0000>来<19\u0000>き<1:\u0000>たんだよ！<1\"\u0000>\nオーブとか<18\u0000>魔女<19\u0000>まじょ<1:\u0000>とか<18\u0000>言<19\u0000>い<1:\u0000>いながらね！",
			"hasEntryInOffsetOffsets": true,
			"noTerminator": false,
			"manualOffset": 0,
			"hasManualOffset": false
		},
		{
			"text_contents": "궷우씯옧꾲⟦D9C3⟧㿉瀤条⑥뜯뛐⿞㻋진⼧엊➼⾵㺷얶눧⟦DEC3⟧딯늿똯➶쎯뜯✾⟦DDC0⟧⟦DEC0⟧糖瀤条⑥➵첰쓞粶켲밧껞뛄눯얰똧ퟞ⻈",
			"hasEntryInOffsetOffsets": true,
			"noTerminator": false,
			"manualOffset": 0,
			"hasManualOffset": false
		},
		{
			"text_contents": "<18\u0000>急<19\u0000>きゅう<1:\u0000>に<18\u0000>何<19\u0000>なに<1:\u0000><18\u0000>言<19\u0000>い<1:\u0000>ってるんですか！？<1\"\u0000>\nあなたが<18\u0000>私<19\u0000>わたし<1:\u0000>の<18\u0000>話<19\u0000>はなし<1:\u0000>も<18\u0000>聞<19\u0000>き<1:\u0000>かずに\n<18\u0000>襲<19\u0000>おそ<1:\u0000>いかかって<18\u0000>来<19\u0000>き<1:\u0000>たんですよ！<1\"\u0000>\nオーブが！<18\u0000>魔女<19\u0000>まじょ<1:\u0000>が！とか<18\u0000>言<19\u0000>い<1:\u0000>いながら！",
			"hasEntryInOffsetOffsets": true,
			"noTerminator": false,
			"manualOffset": 0,
			"hasManualOffset": false
		},
		{
			"text_contents": "궷우ぼ⟅⿆꾲⟃⟦DDD9⟧쌯뷞똾␿慰敧⼤얱쀧⟦DEB6⟧⟦DC2F⟧변⟉쨯볅팧뜯똾⟦DEBD⟧糆딲늿똯➶쎯뜯✾⟦DDC0⟧⟦DEC3⟧횽⑼慰敧딤뀧⟦DECC⟧⟦DEB6⟧콼밧껞⟦DEB6⟧쑼똧눯얰⟦DEB6⟧⟗.",
			"hasEntryInOffsetOffsets": true,
			"noTerminator": true,
			"manualOffset": 0,
			"hasManualOffset": false
		},
		{
			"text_contents": "はあ、<18\u0000>人<19\u0000>ひと<1:\u0000>の<18\u0000>話<19\u0000>はなし<1:\u0000>は<18\u0000>聞<19\u0000>き<1:\u0000>かない。\n<18\u0000>勘違<19\u0000>かんちが<1:\u0000>いはするし……。<1\"\u0000>\nあなた、<18\u0000>私<19\u0000>わたし<1:\u0000>に<18\u0000>襲<19\u0000>おそ<1:\u0000>いかかって<18\u0000>来<19\u0000>き<1:\u0000>たんですよ？\nオーブだとか<18\u0000>魔女<19\u0000>まじょ<1:\u0000>がとか<18\u0000>叫<19\u0000>さけ<1:\u0000>んで。<1\"\u0000>\n……<18\u0000>大丈夫<19\u0000>だいじょうぶ<1:\u0000>ですか？",
			"hasEntryInOffsetOffsets": true,
			"noTerminator": false,
			"manualOffset": 0,
			"hasManualOffset": false
		},
		{
			"text_contents": "⟊粰㻋진⼧엊밧⿜㺷얶⺲⟦DDB6⟧⟁⟦DEB6⟧⟦DCB2⟧봯⟙⺼瀤条⑥넯⟅糀샜욼딯늿➶➶쎯뜯✾⟦DDC0⟧⟦DEC3⟧횽딿뀧⟦DECC⟧⟦DEC0⟧뛄㉼⟏⟦DEBC⟧뚮糞뛄⼧릻⟦DD27⟧⟦DEC3⟧␮慰敧簤⟦DEC0⟧벲껞뀧⟦DECC⟧⟦DEC3⟧㺽㾶",
			"hasEntryInOffsetOffsets": true,
			"noTerminator": false,
			"manualOffset": 0,
			"hasManualOffset": false
		},
		{
			"text_contents": "<18\u0000>何<19\u0000>なに<1:\u0000><18\u0000>言<19\u0000>い<1:\u0000>ってんだ！？<1\"\u0000>\nいきなり<18\u0000>襲<19\u0000>おそ<1:\u0000>いかかって<18\u0000>来<19\u0000>き<1:\u0000>て<18\u0000>暴<19\u0000>あば<1:\u0000>れといて\nそれはねーだろ！<1\"\u0000>\n<18\u0000>本当<19\u0000>ほんとう<1:\u0000>にオーブとか<18\u0000>魔女<19\u0000>まじょ<1:\u0000>だかも<18\u0000>知<19\u0000>し<1:\u0000>らねーからな！",
			"hasEntryInOffsetOffsets": true,
			"noTerminator": false,
			"manualOffset": 0,
			"hasManualOffset": false
		},
		{
			"text_contents": "⟅⿆꾲⟃생㿞瀤条⑥눯얷⟦D827⟧딯➿뚲➶쎯㺷⿃쪱⟦DADE⟧⟄쎲뽼⟦DCDA⟧⟈산㻞糛瀤条⑥츯쓝우딯뀧⟦DECC⟧뛄켯밧껞⟦DEC0⟧펶밯죗뀧ힶ⻅",
			"hasEntryInOffsetOffsets": true,
			"noTerminator": false,
			"manualOffset": 0,
			"hasManualOffset": false
		},
		{
			"text_contents": "どうしちゃったの？<1\"\u0000>\nオーブとか<18\u0000>魔女<19\u0000>まじょ<1:\u0000>とか<18\u0000>言<19\u0000>い<1:\u0000>ってたけど\n<18\u0000>僕<19\u0000>ぼく<1:\u0000>に<18\u0000>襲<19\u0000>おそ<1:\u0000>いかかるほど<18\u0000>大事<19\u0000>だいじ<1:\u0000>なものなの？<1\"\u0000>\n<18\u0000>僕<19\u0000>ぼく<1:\u0000>、<18\u0000>本当<19\u0000>ほんとう<1:\u0000>に<18\u0000>何<19\u0000>なに<1:\u0000>も<18\u0000>知<19\u0000>し<1:\u0000>らないよ。",
			"hasEntryInOffsetOffsets": true,
			"noTerminator": false,
			"manualOffset": 0,
			"hasManualOffset": false
		},
		{
			"text_contents": "⟦DEC4⟧뀧㺼곁삯㿉瀤条⑥➵첰쓞⾶⟏⟦DEBC⟧쒮⾶꾲⟃맀⟦DEC4⟧㉼⟦DECE⟧렧⿆뾵⾲뚶⟦D927⟧쓎⿞⟦DEC0⟧벲엞팯⟉짅␿慰敧⼤⟦DECE⟧렧ぼ⟦DDCE⟧냄⿆씹폆⼧ힼ닅⟖.",
			"hasEntryInOffsetOffsets": true,
			"noTerminator": true,
			"manualOffset": 0,
			"hasManualOffset": false
		},
		{
			"text_contents": "アンタこそ<18\u0000>一体<19\u0000>いったい<1:\u0000><18\u0000>何<19\u0000>なん<1:\u0000>なのよ！<1\"\u0000>\n<18\u0000>人<19\u0000>ひと<1:\u0000>の<18\u0000>話<19\u0000>はなし<1:\u0000>も<18\u0000>聞<19\u0000>き<1:\u0000>かないで\nいきなり<18\u0000>襲<19\u0000>おそ<1:\u0000>いかかって<18\u0000>来<19\u0000>き<1:\u0000>て！<1\"\u0000>\nオーブも<18\u0000>魔女<19\u0000>まじょ<1:\u0000>も<18\u0000>何<19\u0000>なん<1:\u0000>のことだかサッパリよ！",
			"hasEntryInOffsetOffsets": true,
			"noTerminator": false,
			"manualOffset": 0,
			"hasManualOffset": false
		},
		{
			"text_contents": "➱생뾺눯삯얲⟦DD27⟧짅糖瀤条⑥쬯쐾⟉쨯⟅펼뜯똾씧쎲糞눲얷⿘뾵⾲뚶꼧럃쌾⑼慰敧딤뀧⟦DECC⟧⿓⟏⟦DEBC⟧펮씯⟦DD27⟧뫉샄뛞묯쪯⟟훘.",
			"hasEntryInOffsetOffsets": true,
			"noTerminator": true,
			"manualOffset": 0,
			"hasManualOffset": false
		},
		{
			"text_contents": "<18\u0000>失敬<19\u0000>しっけい<1:\u0000>だな！<1\"\u0000>\n<18\u0000>人<19\u0000>ひと<1:\u0000>の<18\u0000>話<19\u0000>はなし<1:\u0000>も<18\u0000>聞<19\u0000>き<1:\u0000>かずオーブンだか<18\u0000>孫<19\u0000>まご<1:\u0000>だか<18\u0000>言<19\u0000>い<1:\u0000>って\n<18\u0000>私<19\u0000>わたし<1:\u0000>に<18\u0000>襲<19\u0000>おそ<1:\u0000>いかかって<18\u0000>来<19\u0000>き<1:\u0000>たではないか！<1\"\u0000>\nまあ、<18\u0000>私<19\u0000>わたし<1:\u0000>にはかすり<18\u0000>傷<19\u0000>きず<1:\u0000>ひとつないが……。",
			"hasEntryInOffsetOffsets": true,
			"noTerminator": false,
			"manualOffset": 0,
			"hasManualOffset": false
		},
		{
			"text_contents": "꾼➹산엞⑼慰敧⼤㻋진⼧엊밧⿓㺷붶糞딲뀧⟦DECC⟧생뛞켯⟦DEBA⟧쀧뛞눯쎯㉼샜욼딯늿뚶꼧럃쀾⟦DEC3⟧⿜닅粶瀤条⑥켯뀧⟦DC7C⟧변⟆⿜붶⟘붷⿞㻋⟄엂뚲⻞",
			"hasEntryInOffsetOffsets": true,
			"noTerminator": false,
			"manualOffset": 0,
			"hasManualOffset": false
		},
		{
			"text_contents": "えー……。\n<18\u0000>人襲<19\u0000>ひとおそ<1:\u0000>っておいて<18\u0000>何<19\u0000>なに<1:\u0000><18\u0000>言<19\u0000>い<1:\u0000>ってるんですか？<1\"\u0000>\n<18\u0000>散々<19\u0000>さんざん<1:\u0000>オーブだか<18\u0000>魔女<19\u0000>まじょ<1:\u0000>だか<18\u0000>叫<19\u0000>さけ<1:\u0000>んでおいて……。<1\"\u0000>\n……<18\u0000>本気<19\u0000>ほんき<1:\u0000>で<18\u0000>言<19\u0000>い<1:\u0000>ってます？",
			"hasEntryInOffsetOffsets": true,
			"noTerminator": false,
			"manualOffset": 0,
			"hasManualOffset": false
		},
		{
			"text_contents": "㥳내粰㕳㻋⿄뾵쎯딯눧⿃⟅닆쎯⟦DDD9⟧⟦DEC3⟧㺽㾶瀤条⑥묯믝⟦DDDE⟧딯뀧⟦DECC⟧⟦DEC0⟧⾶⟏⟦DEBC⟧삮뛞묯➹쏝뗞쎲␮慰敧簤⟦DDCE⟧쎷⿞꾲쿃봧?",
			"hasEntryInOffsetOffsets": true,
			"noTerminator": true,
			"manualOffset": 0,
			"hasManualOffset": false
		},
		{
			"text_contents": "そう<18\u0000>怒<19\u0000>おこ<1:\u0000>るな……\nおそらく、<18\u0000>正気<19\u0000>しょうき<1:\u0000>を<18\u0000>失<19\u0000>うしな<1:\u0000>っていたせいケロ。<1\"\u0000>\nっと、<18\u0000>紹介<19\u0000>しょうかい<1:\u0000>がまだだった……<18\u0000>心<19\u0000>こころ<1:\u0000>して<18\u0000>聞<19\u0000>き<1:\u0000>くケロ。\nオレ<18\u0000>様<19\u0000>さま<1:\u0000>は<17\u0003>{8, MessageNpcName, +}<2F耀>{4, message}。とある<18\u0000>王国<19\u0000>おうこく<1:\u0000>の<18\u0000>王子<19\u0000>おうじ<1:\u0000>ケロ。<1\"\u0000>\nオレ<18\u0000>様<19\u0000>さま<1:\u0000>の<18\u0000>王国<19\u0000>おうこく<1:\u0000>は、「あく」の<18\u0000>力<19\u0000>ちから<1:\u0000>を<18\u0000>持<19\u0000>も<1:\u0000>つ\n「<17\u0003>{9, MonsterParameter, +}<2»耀>{3, name, +}」に<18\u0000>突然襲<19\u0000>とつぜんおそ<1:\u0000>われたケロ。<1\"\u0000>\nそして<18\u0000>勇敢<19\u0000>ゆうかん<1:\u0000>なオレ<18\u0000>様<19\u0000>さま<1:\u0000>に<18\u0000>魔女<19\u0000>まじょ<1:\u0000>めは<18\u0000>卑劣<19\u0000>ひれつ<1:\u0000>な<18\u0000>魔法<19\u0000>まほう<1:\u0000>で\nオレ<18\u0000>様<19\u0000>さま<1:\u0000>をこんな<18\u0000>醜<19\u0000>みにく<1:\u0000>い<18\u0000>姿<19\u0000>すがた<1:\u0000>に<18\u0000>変<19\u0000>か<1:\u0000>えたケロ！！",
			"hasEntryInOffsetOffsets": true,
			"noTerminator": false,
			"manualOffset": 0,
			"hasManualOffset": false
		},
		{
			"text_contents": "",
			"hasEntryInOffsetOffsets": true,
			"noTerminator": false,
			"manualOffset": 0,
			"hasManualOffset": false
		},
		{
			"text_contents": "ひどい！！\nそんな<18\u0000>事<19\u0000>こと<1:\u0000>があったなんて……。",
			"hasEntryInOffsetOffsets": true,
			"noTerminator": false,
			"manualOffset": 0,
			"hasManualOffset": false
		},
		{
			"text_contents": "쓋⟞粲⟦DDBF⟧⟅쒺⟦DEB6⟧넯꼧엀쏝.",
			"hasEntryInOffsetOffsets": true,
			"noTerminator": true,
			"manualOffset": 0,
			"hasManualOffset": false
		},
		{
			"text_contents": "ひどいです！！\nそんな<18\u0000>事<19\u0000>こと<1:\u0000>があったのですか……。",
			"hasEntryInOffsetOffsets": true,
			"noTerminator": false,
			"manualOffset": 0,
			"hasManualOffset": false
		},
		{
			"text_contents": "쓋⟞쎲뷞簾⟦DDBF⟧⟅쒺⟦DEB6⟧넯꼧지⟦DEC3⟧봯✾⺶",
			"hasEntryInOffsetOffsets": true,
			"noTerminator": false,
			"manualOffset": 0,
			"hasManualOffset": false
		},
		{
			"text_contents": "それはまたひどい<18\u0000>話<19\u0000>はなし<1:\u0000>ですね。\n<18\u0000>心中<19\u0000>しんちゅう<1:\u0000>お<18\u0000>察<19\u0000>さっ<1:\u0000>しします。",
			"hasEntryInOffsetOffsets": true,
			"noTerminator": false,
			"manualOffset": 0,
			"hasManualOffset": false
		},
		{
			"text_contents": "⟦DABF⟧⿜샏㉼쓋⟞⾲엊밧⟦DEC3⟧좽밮⟦DD27⟧귁⾰뮵벯밾⟏㺽.",
			"hasEntryInOffsetOffsets": true,
			"noTerminator": true,
			"manualOffset": 0,
			"hasManualOffset": false
		},
		{
			"text_contents": "そいつはひっでー<18\u0000>話<19\u0000>はなし<1:\u0000>だな！！",
			"hasEntryInOffsetOffsets": true,
			"noTerminator": false,
			"manualOffset": 0,
			"hasManualOffset": false
		},
		{
			"text_contents": "늿⟦DCC2⟧쬯쎯⟞⾰엊밧⟦DEC0⟧⻅",
			"hasEntryInOffsetOffsets": true,
			"noTerminator": false,
			"manualOffset": 0,
			"hasManualOffset": false
		},
		{
			"text_contents": "ひどーい！！\nそんなことがあったんだ……。",
			"hasEntryInOffsetOffsets": true,
			"noTerminator": false,
			"manualOffset": 0,
			"hasManualOffset": false
		},
		{
			"text_contents": "쓋⟞늰뽼엝먧뛄⿞➱삯생⻞",
			"hasEntryInOffsetOffsets": true,
			"noTerminator": false,
			"manualOffset": 0,
			"hasManualOffset": false
		},
		{
			"text_contents": "ひどいわ！ひど<18\u0000>過<19\u0000>す<1:\u0000>ぎる！\nそんなの……ホントひどいわ！",
			"hasEntryInOffsetOffsets": true,
			"noTerminator": false,
			"manualOffset": 0,
			"hasManualOffset": false
		},
		{
			"text_contents": "쓋닞⟦DC27⟧쭼⟦DEC4⟧봧⟦DEB7⟧⟦D927⟧뽼엝줧㥼⟦DDCE⟧⿄쓋닞⟦DC27⟧.",
			"hasEntryInOffsetOffsets": true,
			"noTerminator": true,
			"manualOffset": 0,
			"hasManualOffset": false
		},
		{
			"text_contents": "けしからん！\nまったくひどい<18\u0000>話<19\u0000>はなし<1:\u0000>だ！",
			"hasEntryInOffsetOffsets": true,
			"noTerminator": false,
			"manualOffset": 0,
			"hasManualOffset": false
		},
		{
			"text_contents": "벹똾휯⟦DD27⟧콼삯㺸쬯⟦DEC4⟧눧쨯⟅삼⻞",
			"hasEntryInOffsetOffsets": true,
			"noTerminator": false,
			"manualOffset": 0,
			"hasManualOffset": false
		},
		{
			"text_contents": "ええ……<18\u0000>何<19\u0000>なに<1:\u0000>それ<18\u0000>怖<19\u0000>こわ<1:\u0000>い。",
			"hasEntryInOffsetOffsets": true,
			"noTerminator": false,
			"manualOffset": 0,
			"hasManualOffset": false
		},
		{
			"text_contents": "내⾰⟅⿆⟦DABF⟧멼⟜⺲",
			"hasEntryInOffsetOffsets": true,
			"noTerminator": false,
			"manualOffset": 0,
			"hasManualOffset": false
		},
		{
			"text_contents": "……それで、ここでは<18\u0000>何<19\u0000>なに<1:\u0000>をしていたの？",
			"hasEntryInOffsetOffsets": true,
			"noTerminator": false,
			"manualOffset": 0,
			"hasManualOffset": false
		},
		{
			"text_contents": "⟦DABF⟧쌾糞몺⟦DEC3⟧⟦DC27⟧씯옧⾵㺼닃⟀㿉",
			"hasEntryInOffsetOffsets": true,
			"noTerminator": false,
			"manualOffset": 0,
			"hasManualOffset": false
		},
		{
			"text_contents": "……それで。\nここでは<18\u0000>何<19\u0000>なに<1:\u0000>をしていたのですか？",
			"hasEntryInOffsetOffsets": true,
			"noTerminator": false,
			"manualOffset": 0,
			"hasManualOffset": false
		},
		{
			"text_contents": "⟦DABF⟧쌾⻞몺⟦DEC3⟧⟦DC27⟧씯옧⾵㺼닃⟀쏉뷞똾?",
			"hasEntryInOffsetOffsets": true,
			"noTerminator": true,
			"manualOffset": 0,
			"hasManualOffset": false
		},
		{
			"text_contents": "……それで。\nここでは<18\u0000>何<19\u0000>なに<1:\u0000>をしていたのでしょうか？",
			"hasEntryInOffsetOffsets": true,
			"noTerminator": false,
			"manualOffset": 0,
			"hasManualOffset": false
		},
		{
			"text_contents": "⟦DABF⟧쌾⻞몺⟦DEC3⟧⟦DC27⟧씯옧⾵㺼닃⟀쏉볞떮⺶",
			"hasEntryInOffsetOffsets": true,
			"noTerminator": false,
			"manualOffset": 0,
			"hasManualOffset": false
		},
		{
			"text_contents": "それで？\nここでは<18\u0000>何<19\u0000>なに<1:\u0000>してたんだ？",
			"hasEntryInOffsetOffsets": true,
			"noTerminator": false,
			"manualOffset": 0,
			"hasManualOffset": false
		},
		{
			"text_contents": "⟦DABF⟧쌾㿞몺⟦DEC3⟧⟦DC27⟧씯옧㺼샃생㿞",
			"hasEntryInOffsetOffsets": true,
			"noTerminator": false,
			"manualOffset": 0,
			"hasManualOffset": false
		},
		{
			"text_contents": "……それで？\nここでは<18\u0000>何<19\u0000>なに<1:\u0000>をしてたの？",
			"hasEntryInOffsetOffsets": true,
			"noTerminator": false,
			"manualOffset": 0,
			"hasManualOffset": false
		},
		{
			"text_contents": "⟦DABF⟧쌾㿞몺⟦DEC3⟧⟦DC27⟧씯옧⾵㺼샃줧?",
			"hasEntryInOffsetOffsets": true,
			"noTerminator": true,
			"manualOffset": 0,
			"hasManualOffset": false
		},
		{
			"text_contents": "それで……ここでは<18\u0000>何<19\u0000>なに<1:\u0000>をしていたの？",
			"hasEntryInOffsetOffsets": true,
			"noTerminator": false,
			"manualOffset": 0,
			"hasManualOffset": false
		},
		{
			"text_contents": "⟦DABF⟧쌾糞몺⟦DEC3⟧⟦DC27⟧씯옧⾵㺼닃⟀㿉",
			"hasEntryInOffsetOffsets": true,
			"noTerminator": false,
			"manualOffset": 0,
			"hasManualOffset": false
		},
		{
			"text_contents": "……それで、ここでは<18\u0000>何<19\u0000>なに<1:\u0000>をしていたのかね？",
			"hasEntryInOffsetOffsets": true,
			"noTerminator": false,
			"manualOffset": 0,
			"hasManualOffset": false
		},
		{
			"text_contents": "⟦DABF⟧쌾糞몺⟦DEC3⟧⟦DC27⟧씯옧⾵㺼닃⟀뛉㿈",
			"hasEntryInOffsetOffsets": true,
			"noTerminator": false,
			"manualOffset": 0,
			"hasManualOffset": false
		},
		{
			"text_contents": "……それで、ここで<18\u0000>何<19\u0000>なに<1:\u0000>かしてたんですよね？",
			"hasEntryInOffsetOffsets": true,
			"noTerminator": false,
			"manualOffset": 0,
			"hasManualOffset": false
		},
		{
			"text_contents": "⟦DABF⟧쌾糞몺⟦DEC3⟧씯옧⾶㺼샃⟦DD27⟧⟦DEC3⟧횽㿈",
			"hasEntryInOffsetOffsets": true,
			"noTerminator": false,
			"manualOffset": 0,
			"hasManualOffset": false
		},
		{
			"text_contents": "よくわからんが、<18\u0000>正気<19\u0000>しょうき<1:\u0000>を<18\u0000>失<19\u0000>うしな<1:\u0000>っている<18\u0000>間<19\u0000>あいだ<1:\u0000>ずっと\n<18\u0000>頭<19\u0000>あたま<1:\u0000>の<18\u0000>中<19\u0000>なか<1:\u0000>で「オーブを<18\u0000>探<19\u0000>さが<1:\u0000>せ」と<18\u0000>言<19\u0000>い<1:\u0000>われていたケロ。<1\"\u0000>\n<18\u0000>魔女<19\u0000>まじょ<1:\u0000>め。きっとオーブを<18\u0000>手<19\u0000>て<1:\u0000>に<18\u0000>入<19\u0000>い<1:\u0000>れるため\n<18\u0000>王子<19\u0000>おうじ<1:\u0000>であるオレ<18\u0000>様<19\u0000>さま<1:\u0000>を<18\u0000>手足<19\u0000>てあし<1:\u0000>のように<18\u0000>操<19\u0000>あやつ<1:\u0000>って……。",
			"hasEntryInOffsetOffsets": true,
			"noTerminator": false,
			"manualOffset": 0,
			"hasManualOffset": false
		},
		{
			"text_contents": "",
			"hasEntryInOffsetOffsets": true,
			"noTerminator": false,
			"manualOffset": 0,
			"hasManualOffset": false
		},
		{
			"text_contents": "そうなんだ。\nよくわからないけど、<18\u0000>大変<19\u0000>たいへん<1:\u0000>だったね。<1\"\u0000>\nじゃあ、<18\u0000>探<19\u0000>さが<1:\u0000>し<18\u0000>物<19\u0000>もの<1:\u0000>があるから\nボクはもう<18\u0000>行<19\u0000>い<1:\u0000>くね！<1\"\u0000>\nキミもまた<18\u0000>操<19\u0000>あやつ<1:\u0000>られないように\n<18\u0000>気<19\u0000>き<1:\u0000>をつけてね。",
			"hasEntryInOffsetOffsets": true,
			"noTerminator": false,
			"manualOffset": 0,
			"hasManualOffset": false
		},
		{
			"text_contents": "➿얰생⻞⟖⾸뛜⟗닅쒹糞닀⟦DDCD⟧⟦DEC0⟧꼧죀␮慰敧⼤⟦DEBC⟧➬粰뚻볞짓⟦DEB6⟧넯⟦D927⟧ힶ츯⟞⟦DCB8⟧팯뀧눯좸簧瀤条⑥뜧폐㉼샏넯싔⟦DAD7⟧씧횲우뜯➵㻂쎹⻈",
			"hasEntryInOffsetOffsets": true,
			"noTerminator": false,
			"manualOffset": 0,
			"hasManualOffset": false
		},
		{
			"text_contents": "そうですか……。\nよくわかりませんが、<18\u0000>大変<19\u0000>たいへん<1:\u0000>でしたね。<1\"\u0000>\nでは、<18\u0000>探<19\u0000>さが<1:\u0000>し<18\u0000>物<19\u0000>もの<1:\u0000>がありますので<18\u0000>行<19\u0000>い<1:\u0000>きますね。<1\"\u0000>\nあなたもまた<18\u0000>操<19\u0000>あやつ<1:\u0000>られないよう\nどうか<18\u0000>気<19\u0000>き<1:\u0000>をつけて。",
			"hasEntryInOffsetOffsets": true,
			"noTerminator": false,
			"manualOffset": 0,
			"hasManualOffset": false
		},
		{
			"text_contents": "➿쎰뷞똾혮렧⟦DC2F⟧⟦D8B6⟧뻏⟦DD27⟧⟦DEB6⟧쁼춲쏝⟞㺼죀␮慰敧쌤⟦DCDE⟧뭼⟦DEB6⟧펼뛉⿞⟦D8B1⟧⟏즽⟦DEC3⟧눯쾷봧⻈瀤条⑥넯⟅폀㉼샏넯싔⟦DAD7⟧씧횲粰쐲⟞뚰뜯➵㻂쎹.",
			"hasEntryInOffsetOffsets": true,
			"noTerminator": true,
			"manualOffset": 0,
			"hasManualOffset": false
		},
		{
			"text_contents": "なるほど。よくわかりませんが\n<18\u0000>大変<19\u0000>たいへん<1:\u0000>だったと<18\u0000>伝<19\u0000>つた<1:\u0000>わりました。<1\"\u0000>\nそれでは、<18\u0000>私<19\u0000>わたし<1:\u0000>は<18\u0000>探<19\u0000>さが<1:\u0000>し<18\u0000>物<19\u0000>もの<1:\u0000>がありますので\nこれにて<18\u0000>失礼<19\u0000>しつれい<1:\u0000>します。<1\"\u0000>\nまた<18\u0000>操<19\u0000>あやつ<1:\u0000>られないよう\nどうかお<18\u0000>気<19\u0000>き<1:\u0000>をつけて。",
			"hasEntryInOffsetOffsets": true,
			"noTerminator": false,
			"manualOffset": 0,
			"hasManualOffset": false
		},
		{
			"text_contents": "⟦D9C5⟧쓎⻞⟖⾸뛜쿘➾뛝糞쀲춲생⟞삯⿄㻂⟦DCC0⟧쿘밧쀾␮慰敧⼤⟦DABF⟧⟦DEC3⟧⟦DC27⟧⟦DC7C⟧변⿜뚻볞짓⟦DEB6⟧넯쿘봧쏉糞먲웚쌧밯숾⟦DA27⟧벰뷏⸾瀤条⑥켯⿀풱ퟂ⟚닅냖㉼⟦DEC4⟧뀧⾶략➵㻂쎹.",
			"hasEntryInOffsetOffsets": true,
			"noTerminator": true,
			"manualOffset": 0,
			"hasManualOffset": false
		},
		{
			"text_contents": "そうだったのかー。\nまあよくわからねーけど<18\u0000>大変<19\u0000>たいへん<1:\u0000>だったな！<1\"\u0000>\nじゃ、<18\u0000>俺<19\u0000>おれ<1:\u0000>は<18\u0000>探<19\u0000>さが<1:\u0000>し<18\u0000>物<19\u0000>もの<1:\u0000>の<18\u0000>途中<19\u0000>とちゅう<1:\u0000>だし\nもう<18\u0000>行<19\u0000>い<1:\u0000>くから！<1\"\u0000>\nまた<18\u0000>操<19\u0000>あやつ<1:\u0000>られるんじゃねーぞ！",
			"hasEntryInOffsetOffsets": true,
			"noTerminator": false,
			"manualOffset": 0,
			"hasManualOffset": false
		},
		{
			"text_contents": "➿산꿞지똯뀧켮뀧혯렧⟦DC2F⟧ힶ젧린⟦DEC4⟧쀯춲생⟞삯糅瀤条⑥⟦DEBC⟧粬⟦DAB5⟧⿜뚻볞짓⿉쇄낭⟦DEC0⟧밧팯뀧눯㺸똧糗瀤条⑥켯⿀풱ퟂ⟚⟦DDD9⟧⟦DEBC⟧⾬⟈뾰⻞",
			"hasEntryInOffsetOffsets": true,
			"noTerminator": false,
			"manualOffset": 0,
			"hasManualOffset": false
		},
		{
			"text_contents": "そっかー<18\u0000>難<19\u0000>むずか<1:\u0000>しい<18\u0000>話<19\u0000>はなし<1:\u0000>はよくわからないけど\n<18\u0000>大変<19\u0000>たいへん<1:\u0000>だったんだね。<1\"\u0000>\nそれじゃ<18\u0000>僕<19\u0000>ぼく<1:\u0000>、<18\u0000>探<19\u0000>さが<1:\u0000>し<18\u0000>物<19\u0000>もの<1:\u0000>の<18\u0000>続<19\u0000>つづ<1:\u0000>きに<18\u0000>行<19\u0000>い<1:\u0000>くから。<1\"\u0000>\nまた<18\u0000>操<19\u0000>あやつ<1:\u0000>られないように<18\u0000>気<19\u0000>き<1:\u0000>を<18\u0000>付<19\u0000>つ<1:\u0000>けてねー。",
			"hasEntryInOffsetOffsets": true,
			"noTerminator": false,
			"manualOffset": 0,
			"hasManualOffset": false
		},
		{
			"text_contents": "➿뚯粰턲⟦DEBD⟧벶⾲엊밧⿜⟖⾸뛜⟗닅쒹糞쀲춲생⟞삯생죞␮慰敧⼤⟦DABF⟧⟦DEBC⟧⾬⟦DECE⟧렧뭼⟦DEB6⟧펼짉숯⟦DEC2⟧욷눯㺸똧⻗瀤条⑥켯⿀➱싔⟦DAD7⟧씧횲우ぼ떷숧뤾죃.",
			"hasEntryInOffsetOffsets": true,
			"noTerminator": true,
			"manualOffset": 0,
			"hasManualOffset": false
		},
		{
			"text_contents": "……そうだったの。\n<18\u0000>大変<19\u0000>たいへん<1:\u0000>だったわね。<1\"\u0000>\nよくわからないけど、\nまた<18\u0000>操<19\u0000>あやつ<1:\u0000>られないように<18\u0000>気<19\u0000>き<1:\u0000>をつけなさいね。<1\"\u0000>\nそれじゃアタシ、<18\u0000>探<19\u0000>さが<1:\u0000>し<18\u0000>物<19\u0000>もの<1:\u0000>があるから<18\u0000>行<19\u0000>い<1:\u0000>くわね。",
			"hasEntryInOffsetOffsets": true,
			"noTerminator": false,
			"manualOffset": 0,
			"hasManualOffset": false
		},
		{
			"text_contents": "➿산꿞지쀮춲생⟞삯죜␮慰敧⼤⟖⾸뛜⟗닅쒹糞샏넯싔⟦DAD7⟧씧횲우뜯⾵㻂얹➻좲␮慰敧⼤⟦DABF⟧⟦DEBC⟧⾬삱粼뚻볞짓⟦DEB6⟧넯⟦D927⟧ힶぼ뢲⟜⻈",
			"hasEntryInOffsetOffsets": true,
			"noTerminator": false,
			"manualOffset": 0,
			"hasManualOffset": false
		},
		{
			"text_contents": "まあなんというか、<18\u0000>災難<19\u0000>さいなん<1:\u0000>であったな。<1\"\u0000>\nでは<18\u0000>私<19\u0000>わたし<1:\u0000>は<18\u0000>探<19\u0000>さが<1:\u0000>し<18\u0000>物<19\u0000>もの<1:\u0000>があるのでな、<18\u0000>失礼<19\u0000>しつれい<1:\u0000>する。<1\"\u0000>\nもう<18\u0000>操<19\u0000>あやつ<1:\u0000>られないようにな。",
			"hasEntryInOffsetOffsets": true,
			"noTerminator": false,
			"manualOffset": 0,
			"hasManualOffset": false
		},
		{
			"text_contents": "⟏⾰⟅쓝뎲粶늻⟅쏝⿞➱삯⻅瀤条⑥⟦DEC3⟧糜⟦DC30⟧변⿜뚻볞짓⟦DEB6⟧넯⟦D927⟧쏉엞뱼숾⟦DA27⟧붰⻙瀤条⑥팯뀧ぼ풱ퟂ⟚닅혯뀧없.",
			"hasEntryInOffsetOffsets": true,
			"noTerminator": true,
			"manualOffset": 0,
			"hasManualOffset": false
		},
		{
			"text_contents": "まあ……<18\u0000>災難<19\u0000>さいなん<1:\u0000>でしたね。<1\"\u0000>\nでは<18\u0000>私<19\u0000>わたし<1:\u0000>はこれで……\n<18\u0000>探<19\u0000>さが<1:\u0000>し<18\u0000>物<19\u0000>もの<1:\u0000>をみつけないといけないので。<1\"\u0000>\n<18\u0000>次<19\u0000>つぎ<1:\u0000>は<18\u0000>操<19\u0000>あやつ<1:\u0000>られないといいですね。",
			"hasEntryInOffsetOffsets": true,
			"noTerminator": false,
			"manualOffset": 0,
			"hasManualOffset": false
		},
		{
			"text_contents": "⟏粰늻⟅쏝볞쀾⻈瀤条⑥⟦DEC3⟧糜⟦DC30⟧변⿜⟦DABA⟧⟦DEC3⟧뭼⟦DEB6⟧펼뗉퀯㻂얹눧⿄릲⟅즲⟦DEC3⟧␮慰敧⼤럂⟞⿜풱ퟂ⟚닅⿄➲쎰뷞⻈",
			"hasEntryInOffsetOffsets": true,
			"noTerminator": false,
			"manualOffset": 0,
			"hasManualOffset": false
		},
		{
			"text_contents": "お<18\u0000>前<19\u0000>まえ<1:\u0000>、<18\u0000>待<19\u0000>ま<1:\u0000>つケロ。<1\"\u0000>\n<18\u0000>魔女<19\u0000>まじょ<1:\u0000>がオーブを<18\u0000>集<19\u0000>あつ<1:\u0000>め、<18\u0000>何<19\u0000>なに<1:\u0000>を<18\u0000>目論<19\u0000>もくろ<1:\u0000>んでいるかは\nわからんが、このままでは<18\u0000>腹<19\u0000>はら<1:\u0000>の<18\u0000>虫<19\u0000>むし<1:\u0000>がおさまらん。<1\"\u0000>\nお<18\u0000>前<19\u0000>まえ<1:\u0000>、ヤツよりも<18\u0000>先回<19\u0000>さきまわ<1:\u0000>りして\nオーブを<18\u0000>集<19\u0000>あつ<1:\u0000>めるケロ。",
			"hasEntryInOffsetOffsets": true,
			"noTerminator": false,
			"manualOffset": 0,
			"hasManualOffset": false
		},
		{
			"text_contents": "",
			"hasEntryInOffsetOffsets": true,
			"noTerminator": false,
			"manualOffset": 0,
			"hasManualOffset": false
		},
		{
			"text_contents": "えっ、でもボク、<18\u0000>他<19\u0000>ほか<1:\u0000>に<18\u0000>探<19\u0000>さが<1:\u0000>し<18\u0000>物<19\u0000>もの<1:\u0000>があるし……。<1\"\u0000>\nそんな<18\u0000>恐<19\u0000>こわ<1:\u0000>い<18\u0000>魔女<19\u0000>まじょ<1:\u0000>が<18\u0000>探<19\u0000>さが<1:\u0000>しているなら\nさっきみたいに<18\u0000>怖<19\u0000>こわ<1:\u0000>い<18\u0000>目<19\u0000>め<1:\u0000>に<18\u0000>合<19\u0000>あ<1:\u0000>うかも……。",
			"hasEntryInOffsetOffsets": true,
			"noTerminator": false,
			"manualOffset": 0,
			"hasManualOffset": false
		},
		{
			"text_contents": "꾴썼⟞⿓⟦DECE⟧렧칼욶묯⟦DEB6⟧펼뛉⿞➱볙␮慰敧⼤⟦DDBF⟧⿅⟦DCBA⟧눧켯밧껞⟦DEB6⟧묯⟦DEB6⟧㺼닃엙휧㉼➻랯샐욲먯⟜튲⿆➱뚳⻓",
			"hasEntryInOffsetOffsets": true,
			"noTerminator": false,
			"manualOffset": 0,
			"hasManualOffset": false
		},
		{
			"text_contents": "えっ、ですが……。\n<18\u0000>私<19\u0000>わたし<1:\u0000>にも<18\u0000>頼<19\u0000>たの<1:\u0000>まれた<18\u0000>探<19\u0000>さが<1:\u0000>し<18\u0000>物<19\u0000>もの<1:\u0000>がありますし。<1\"\u0000>\nそんな<18\u0000>恐<19\u0000>こわ<1:\u0000>い<18\u0000>魔女<19\u0000>まじょ<1:\u0000>が<18\u0000>探<19\u0000>さが<1:\u0000>しているなら\nさっきみたいに<18\u0000>怖<19\u0000>こわ<1:\u0000>い<18\u0000>目<19\u0000>め<1:\u0000>に<18\u0000>合<19\u0000>あ<1:\u0000>うかと<18\u0000>思<19\u0000>おも<1:\u0000>うと。",
			"hasEntryInOffsetOffsets": true,
			"noTerminator": false,
			"manualOffset": 0,
			"hasManualOffset": false
		},
		{
			"text_contents": "꾴썼⟞뚽⻞샜욼팧쀯쿉⟚⿀뚻볞짓⟦DEB6⟧넯쿘봧밾␮慰敧⼤⟦DDBF⟧⿅⟦DCBA⟧눧켯밧껞⟦DEB6⟧묯⟦DEB6⟧㺼닃엙휧㉼➻랯샐욲먯⟜⾲⟒⿆➱뚳⿄펵댧⻄",
			"hasEntryInOffsetOffsets": true,
			"noTerminator": false,
			"manualOffset": 0,
			"hasManualOffset": false
		},
		{
			"text_contents": "それは、<18\u0000>何<19\u0000>なん<1:\u0000>と<18\u0000>申<19\u0000>もう<1:\u0000>しますか……。\n<18\u0000>私<19\u0000>わたし<1:\u0000>にも<18\u0000>他<19\u0000>ほか<1:\u0000>に<18\u0000>頼<19\u0000>たの<1:\u0000>まれた<18\u0000>探<19\u0000>さが<1:\u0000>し<18\u0000>物<19\u0000>もの<1:\u0000>がありまして。<1\"\u0000>\nましてやそんな<18\u0000>恐<19\u0000>こわ<1:\u0000>い<18\u0000>魔女<19\u0000>まじょ<1:\u0000>が<18\u0000>集<19\u0000>あつ<1:\u0000>めているなら\nさっきのように<18\u0000>襲<19\u0000>おそ<1:\u0000>われでもしたら……。",
			"hasEntryInOffsetOffsets": true,
			"noTerminator": false,
			"manualOffset": 0,
			"hasManualOffset": false
		},
		{
			"text_contents": "⟦DABF⟧糜⟅쓝⿓벳뷏똾⟦DC2E⟧변⟆⿓뛎⿆지⟦DACF⟧쀧묯⟦DEB6⟧펼뛉⿞⟦D8B1⟧⟏㺼⻃瀤条⑥켯밧쌾糔뼲엝먯⟜⾲⟏⟦DEBC⟧뚮⿞슱툧닃엙糗묲꼧즷냖⿆뾵⟦DADC⟧⟦DEC3⟧팧밯쀾휧.",
			"hasEntryInOffsetOffsets": true,
			"noTerminator": true,
			"manualOffset": 0,
			"hasManualOffset": false
		},
		{
			"text_contents": "えーでも<18\u0000>俺<19\u0000>おれ<1:\u0000>、<18\u0000>他<19\u0000>ほか<1:\u0000>に<18\u0000>頼<19\u0000>たの<1:\u0000>まれた<18\u0000>探<19\u0000>さが<1:\u0000>し<18\u0000>物<19\u0000>もの<1:\u0000>あるし。<1\"\u0000>\nそれに<18\u0000>魔女<19\u0000>まじょ<1:\u0000>が<18\u0000>必死<19\u0000>ひっし<1:\u0000>で<18\u0000>集<19\u0000>あつ<1:\u0000>めているんだろ？\n<18\u0000>何<19\u0000>なん<1:\u0000>だか<18\u0000>恐<19\u0000>こわ<1:\u0000>そうだしな……。",
			"hasEntryInOffsetOffsets": true,
			"noTerminator": false,
			"manualOffset": 0,
			"hasManualOffset": false
		},
		{
			"text_contents": "내粰⟦DEC3⟧팧딯⟦DA27⟧칼욶쀯쿉⟦DA27⟧⿀뚻볞짓넯⟦D927⟧⺼瀤条⑥뼯웚㉼⟏⟦DEBC⟧뚮⿞꿋쎼⿞슱툧닃⟦DDD9⟧쀯⟞㿛⟅생뛞먯뿜딧쀯볞⻅",
			"hasEntryInOffsetOffsets": true,
			"noTerminator": false,
			"manualOffset": 0,
			"hasManualOffset": false
		},
		{
			"text_contents": "うーん……<18\u0000>今<19\u0000>いま<1:\u0000>、<18\u0000>他<19\u0000>ほか<1:\u0000>の<18\u0000>探<19\u0000>さが<1:\u0000>し<18\u0000>物中<19\u0000>ものちゅう<1:\u0000>だし。<1\"\u0000>\nそれに<18\u0000>恐<19\u0000>こわ<1:\u0000>い<18\u0000>魔女<19\u0000>まじょ<1:\u0000>も<18\u0000>集<19\u0000>あつ<1:\u0000>めてるんだよね。\n<18\u0000>先<19\u0000>さき<1:\u0000>に<18\u0000>集<19\u0000>あつ<1:\u0000>めることなんてできるのかな。",
			"hasEntryInOffsetOffsets": true,
			"noTerminator": false,
			"manualOffset": 0,
			"hasManualOffset": false
		},
		{
			"text_contents": "낳⟦DDB0⟧뉼켧㉼뛎⿉뚻볞짓귁⾰⟦DEC0⟧밧␮慰敧⼤⟦DABF⟧糆먲⟜⾲⟏⟦DEBC⟧펮넯⟂쏒⟦DDD9⟧⟦DEC0⟧죖묮욷넯틂⟦D927⟧먯⟄⟦DDC5⟧⿃⟦DEC3⟧➷짙얶.",
			"hasEntryInOffsetOffsets": true,
			"noTerminator": true,
			"manualOffset": 0,
			"hasManualOffset": false
		},
		{
			"text_contents": "<18\u0000>困<19\u0000>こま<1:\u0000>ったわねえ。\n<18\u0000>今<19\u0000>いま<1:\u0000>は<18\u0000>他<19\u0000>ほか<1:\u0000>の<18\u0000>探<19\u0000>さが<1:\u0000>し<18\u0000>物<19\u0000>もの<1:\u0000>してるし。<1\"\u0000>\nそれに<18\u0000>恐<19\u0000>こわ<1:\u0000>そうな<18\u0000>魔女<19\u0000>まじょ<1:\u0000>より<18\u0000>先<19\u0000>さき<1:\u0000>に<18\u0000>集<19\u0000>あつ<1:\u0000>めたら\nどんな<18\u0000>恐<19\u0000>おそ<1:\u0000>ろしい<18\u0000>目<19\u0000>め<1:\u0000>に<18\u0000>合<19\u0000>あ<1:\u0000>うのか……！",
			"hasEntryInOffsetOffsets": true,
			"noTerminator": false,
			"manualOffset": 0,
			"hasManualOffset": false
		},
		{
			"text_contents": "쾺꼧⟦DCC0⟧냈눮켧⿜뛎⿉뚻볞짓밯쌾⟙⺼瀤条⑥뼯웚㉼⟦DCBA⟧➿억켯밧껞⟦D8D6⟧묯욷넯⟂샒糗쐲⟞엝딯⟦DBBF⟧➼⾲⟒⿆➱즳⺶",
			"hasEntryInOffsetOffsets": true,
			"noTerminator": false,
			"manualOffset": 0,
			"hasManualOffset": false
		},
		{
			"text_contents": "なぜ<18\u0000>私<19\u0000>わたし<1:\u0000>が<18\u0000>探<19\u0000>さが<1:\u0000>さなければならない。<1\"\u0000>\nそれに<18\u0000>今<19\u0000>いま<1:\u0000>は<18\u0000>他<19\u0000>ほか<1:\u0000>の<18\u0000>探<19\u0000>さが<1:\u0000>し<18\u0000>物中<19\u0000>ものちゅう<1:\u0000>だ。\n<18\u0000>魔女<19\u0000>まじょ<1:\u0000>は<18\u0000>恐<19\u0000>こわ<1:\u0000>くはないが、<18\u0000>他<19\u0000>ほか<1:\u0000>をあたりたまえ。",
			"hasEntryInOffsetOffsets": true,
			"noTerminator": false,
			"manualOffset": 0,
			"hasManualOffset": false
		},
		{
			"text_contents": "⟅⟦DEBE⟧⟦DC2F⟧변⟦DEB6⟧묯⟦DEB6⟧얻뤧쫚⿞ퟅ씧⺲瀤条⑥뼯웚㉼➲⟦DCCF⟧츯즶묯⟦DEB6⟧펼쇉낭⟦DEC0⟧켮밧껞⿜➺룜⿜⟅뚲糞뛎⾵삱⟘쿀⺴",
			"hasEntryInOffsetOffsets": true,
			"noTerminator": false,
			"manualOffset": 0,
			"hasManualOffset": false
		},
		{
			"text_contents": "えー……ただでさえ<18\u0000>他<19\u0000>ほか<1:\u0000>の<18\u0000>探<19\u0000>さが<1:\u0000>し<18\u0000>物<19\u0000>もの<1:\u0000>してるのに。<1\"\u0000>\nそれに<18\u0000>恐<19\u0000>こわ<1:\u0000>い<18\u0000>魔女<19\u0000>まじょ<1:\u0000>より<18\u0000>先<19\u0000>さき<1:\u0000>に<18\u0000>集<19\u0000>あつ<1:\u0000>めるって\n<18\u0000>無茶<19\u0000>むちゃ<1:\u0000>だって……。",
			"hasEntryInOffsetOffsets": true,
			"noTerminator": false,
			"manualOffset": 0,
			"hasManualOffset": false
		},
		{
			"text_contents": "내粰⟀⟦DEC0⟧⟦DEC3⟧뒻츯즶묯⟦DEB6⟧펼⿉㺼⟦D9C3⟧줧⻆瀤条⑥뼯웚㉼⟦DCBA⟧눧켯밧껞⟦D8D6⟧묯욷넯틂⟦D927⟧쎯㉼⟑곁⟦DEC0⟧쎯.",
			"hasEntryInOffsetOffsets": true,
			"noTerminator": true,
			"manualOffset": 0,
			"hasManualOffset": false
		},
		{
			"text_contents": "<18\u0000>卑劣<19\u0000>ひれつ<1:\u0000>な<18\u0000>魔女<19\u0000>まじょ<1:\u0000>がこの<18\u0000>世界<19\u0000>せかい<1:\u0000>を<18\u0000>脅<19\u0000>おびや<1:\u0000>かすかもしれんケロ！\n<18\u0000>四<19\u0000>し<1:\u0000>の<18\u0000>五<19\u0000>ご<1:\u0000>の<18\u0000>言<19\u0000>い<1:\u0000>わず<18\u0000>急<19\u0000>いそ<1:\u0000>いで<18\u0000>集<19\u0000>あつ<1:\u0000>めるケロ！",
			"hasEntryInOffsetOffsets": true,
			"noTerminator": false,
			"manualOffset": 0,
			"hasManualOffset": false
		},
		{
			"text_contents": "",
			"hasEntryInOffsetOffsets": true,
			"noTerminator": false,
			"manualOffset": 0,
			"hasManualOffset": false
		},
		{
			"text_contents": "なぜ<18\u0000>断<19\u0000>ことわ<1:\u0000>るケロ？\nオレ<18\u0000>様<19\u0000>さま<1:\u0000>から<18\u0000>直々<19\u0000>じきじき<1:\u0000>の<18\u0000>命<19\u0000>めい<1:\u0000>を<18\u0000>光栄<19\u0000>こうえい<1:\u0000>に<18\u0000>思<19\u0000>おも<1:\u0000>うケロ。",
			"hasEntryInOffsetOffsets": true,
			"noTerminator": false,
			"manualOffset": 0,
			"hasManualOffset": false
		},
		{
			"text_contents": "",
			"hasEntryInOffsetOffsets": true,
			"noTerminator": false,
			"manualOffset": 0,
			"hasManualOffset": false
		},
		{
			"text_contents": "ケロ！よい<18\u0000>返事<19\u0000>へんじ<1:\u0000>ケロ。\nそれでこそオレ<18\u0000>様<19\u0000>さま<1:\u0000>が<18\u0000>見<19\u0000>み<1:\u0000><18\u0000>込<19\u0000>こ<1:\u0000>んだ、<18\u0000>電波人間<19\u0000>でんぱにんげん<1:\u0000>ケロ！",
			"hasEntryInOffsetOffsets": true,
			"noTerminator": false,
			"manualOffset": 0,
			"hasManualOffset": false
		},
		{
			"text_contents": "",
			"hasEntryInOffsetOffsets": true,
			"noTerminator": false,
			"manualOffset": 0,
			"hasManualOffset": false
		},
		{
			"text_contents": "う～ん……よかったのかなこれで。\n<18\u0000>引<19\u0000>ひ<1:\u0000>き<18\u0000>受<19\u0000>う<1:\u0000>けたのはいいけど、どうしよう？<1\"\u0000>\n<18\u0000>情報通<19\u0000>じょうほうつう<1:\u0000>の<17\u0003>{8, MessageNpcName, +}<2\u0001耀>{4, message}さんならヒントになる<18\u0000>事<19\u0000>こと<1:\u0000>くらい\n<18\u0000>知<19\u0000>し<1:\u0000>ってるかもしれないから<18\u0000>聞<19\u0000>き<1:\u0000>いてみようかな？",
			"hasEntryInOffsetOffsets": true,
			"noTerminator": false,
			"manualOffset": 0,
			"hasManualOffset": false
		},
		{
			"text_contents": "㥓➳낰糝㕓⟖꾶지얶먯⟚⟦DEC3⟧쬮뜾➳삹⟦DCC9⟧눯눧쒹糞쐰⟞벰냖␮慰敧⼤⟦DEBC⟧낮냎냂⿉洤獥慳敧䴺獥慳敧灎乣浡㩥ㄲ㜴㠴㘳㤴瘺楯散묤엝휧㉼⟋쓝⿆⟅뫙룄닗밯쎯뛙팧밯엚➲ힶ㉼늷탃⟖뚰㿅",
			"hasEntryInOffsetOffsets": true,
			"noTerminator": false,
			"manualOffset": 0,
			"hasManualOffset": false
		},
		{
			"text_contents": "……よかったんでしょうか。<18\u0000>引<19\u0000>ひ<1:\u0000>き<18\u0000>受<19\u0000>う<1:\u0000>けて。\nただ、<18\u0000>集<19\u0000>あつ<1:\u0000>めると<18\u0000>言<19\u0000>い<1:\u0000>ってもどうしましょう。<1\"\u0000>\n<18\u0000>情報通<19\u0000>じょうほうつう<1:\u0000>の<17\u0003>{8, MessageNpcName, +}<2\u0001耀>{4, message}さんならヒントになるような<18\u0000>事<19\u0000>こと<1:\u0000>\n<18\u0000>知<19\u0000>し<1:\u0000>ってるかもしれませんから<18\u0000>聞<19\u0000>き<1:\u0000>いてみますか。",
			"hasEntryInOffsetOffsets": true,
			"noTerminator": false,
			"manualOffset": 0,
			"hasManualOffset": false
		},
		{
			"text_contents": "⟖꾶⟦DDC0⟧⟦DEC3⟧꺼뚵쬮뜾➳쎹쀮쀧糞슱⟒쓙눯쎯팧쐯⟞벰볏떮␮慰敧⼤⟦DEBC⟧낮냎냂⿉洤獥慳敧䴺獥慳敧灎乣浡㩥ㄲ㜴㠴㘳㤴瘺楯散묤엝휧㉼⟋쓝⿆⟅훙얰쒺밯쎯⟙펶밯쿚➾뛝糗뜲쎲쿐봧똾.",
			"hasEntryInOffsetOffsets": true,
			"noTerminator": true,
			"manualOffset": 0,
			"hasManualOffset": false
		},
		{
			"text_contents": "<18\u0000>何<19\u0000>なん<1:\u0000>だか<18\u0000>押<19\u0000>お<1:\u0000>し<18\u0000>切<19\u0000>き<1:\u0000>られた<18\u0000>気分<19\u0000>きぶん<1:\u0000>です。\nさて、<18\u0000>実際<19\u0000>じっさい<1:\u0000>どうしたものか……。<1\"\u0000>\n<18\u0000>情報通<19\u0000>じょうほうつう<1:\u0000>の<17\u0003>{8, MessageNpcName, +}<2\u0001耀>{4, message}さんであれば<18\u0000>何<19\u0000>なに<1:\u0000>かヒントを\n<18\u0000>知<19\u0000>し<1:\u0000>っているかもしれません。<18\u0000>聞<19\u0000>き<1:\u0000>いてみますか。",
			"hasEntryInOffsetOffsets": true,
			"noTerminator": false,
			"manualOffset": 0,
			"hasManualOffset": false
		},
		{
			"text_contents": "⟅생뛞딯㺼ힷ⟦DA27⟧⿀➷⟦DECC⟧쏝뷞⸾쎻뱼꿞늻쐯⟞벰쀾짓⺶瀤条⑥밯껞캰슰즰␯敭獳条㩥敍獳条乥捰慎敭㈺㐱㐷㌸㐶㨹潶捩⑥⟦DDBB⟧⟦DEC3⟧➱쫚糞씲옧⾶⟋쓝⾵꾼닃⟙펶밯쿚⟦DDBE⟧뜮쎲쿐봧똾.",
			"hasEntryInOffsetOffsets": true,
			"noTerminator": true,
			"manualOffset": 0,
			"hasManualOffset": false
		},
		{
			"text_contents": "なーんか<18\u0000>釈然<19\u0000>しゃくぜん<1:\u0000>としねーけど。まーいいや。\nで、<18\u0000>探<19\u0000>さが<1:\u0000>すっつってもどーすっかなー。<1\"\u0000>\n<17\u0003>{8, MessageNpcName, +}<2\u0001耀>{4, message}さんなら<18\u0000>情報通<19\u0000>じょうほうつう<1:\u0000>だしヒントくらいは\n<18\u0000>知<19\u0000>し<1:\u0000>ってるかも？<18\u0000>聞<19\u0000>き<1:\u0000>いてみっか！",
			"hasEntryInOffsetOffsets": true,
			"noTerminator": false,
			"manualOffset": 0,
			"hasManualOffset": false
		},
		{
			"text_contents": "냅⟦DD2F⟧⾶겼뺸⟦DDDE⟧쐯좼뀧쒹⻞냏눯뀧⻔⟦DEC3⟧뭼⟦DEB6⟧➽⾯꿂폃쐯⟞붰뚯냅␮慰敧␤敭獳条㩥敍獳条乥捰慎敭㈺㐱㐷㌸㐶㨹潶捩⑥⟦DDBB⟧⟅⿗⟦DEBC⟧낮냎냂⟦DEC0⟧밧㉼⟋쓝ힸ⟦DCB2⟧밯쎯뛙팧뜿쎲⟐뚯.",
			"hasEntryInOffsetOffsets": true,
			"noTerminator": true,
			"manualOffset": 0,
			"hasManualOffset": false
		},
		{
			"text_contents": "うーん。<18\u0000>良<19\u0000>よ<1:\u0000>かったのかなこれで？\nでもどうやって<18\u0000>探<19\u0000>さが<1:\u0000>そう……。<1\"\u0000>\n<17\u0003>{8, MessageNpcName, +}<2\u0001耀>{4, message}さんなら<18\u0000>情報<19\u0000>じょうほう<1:\u0000>たくさん<18\u0000>知<19\u0000>し<1:\u0000>ってるから\nヒントぐらいは<18\u0000>聞<19\u0000>き<1:\u0000>けるかな？",
			"hasEntryInOffsetOffsets": true,
			"noTerminator": false,
			"manualOffset": 0,
			"hasManualOffset": false
		},
		{
			"text_contents": "➳⟦DDB0⟧혮똧삯뛉⿅⟦DABA⟧⟦DEC3⟧쌿⟞⿓⟦DEC4⟧뀧꿔⿃뚻뿞딧␮慰敧␤敭獳条㩥敍獳条乥捰慎敭㈺㐱㐷㌸㐶㨹潶捩⑥⟦DDBB⟧ퟅ㉼⟦DEBC⟧낮냎쀯뮸⿝꾼⟦D9C3⟧똧糗쬲⟦DD27⟧룄ퟞ⟦DCB2⟧뜯뤾뛙씧?",
			"hasEntryInOffsetOffsets": true,
			"noTerminator": true,
			"manualOffset": 0,
			"hasManualOffset": false
		},
		{
			"text_contents": "うーん。なんだか<18\u0000>複雑<19\u0000>ふくざつ<1:\u0000>だわぁ。\nそれにしても、どう<18\u0000>探<19\u0000>さが<1:\u0000>そうかしら。<1\"\u0000>\n<18\u0000>情報通<19\u0000>じょうほうつう<1:\u0000>の<17\u0003>{8, MessageNpcName, +}<2\u0001耀>{4, message}さんがヒントでも<18\u0000>知<19\u0000>し<1:\u0000>ってると\n<18\u0000>良<19\u0000>い<1:\u0000>いんだけど、<18\u0000>聞<19\u0000>き<1:\u0000>くだけ<18\u0000>聞<19\u0000>き<1:\u0000>いてみましょう。",
			"hasEntryInOffsetOffsets": true,
			"noTerminator": false,
			"manualOffset": 0,
			"hasManualOffset": false
		},
		{
			"text_contents": "➳⟦DDB0⟧씮⟦DD27⟧⟦DEC0⟧⾶㻌뮸싞⟦DEC0⟧⟦DC27⟧넯뼮웚㺼⟃糓⟦DEC4⟧뀧묯⟦DEB6⟧➿뚵ힼ␮慰敧⼤⟦DEBC⟧낮냎냂⿉洤獥慳敧䴺獥慳敧灎乣浡㩥ㄲ㜴㠴㘳㤴瘺楯散묤뛝糞쬲⟦DD27⟧쏄폞밯쎯⟙⿄➲⟦DDB2⟧⟦DEC0⟧쒹糞㺷삸맞뜯쎲쿐꺼딧.",
			"hasEntryInOffsetOffsets": true,
			"noTerminator": true,
			"manualOffset": 0,
			"hasManualOffset": false
		},
		{
			"text_contents": "むむむ……なんだか<18\u0000>釈然<19\u0000>しゃくぜん<1:\u0000>とせんが……\nまあいいとして、どう<18\u0000>探<19\u0000>さが<1:\u0000>すかな。<1\"\u0000>\nやはり<18\u0000>情報通<19\u0000>じょうほうつう<1:\u0000>の<18\u0000>彼<19\u0000>かれ<1:\u0000>に<18\u0000>聞<19\u0000>き<1:\u0000>くのが<18\u0000>一番<19\u0000>いちばん<1:\u0000>だろうか。\n<18\u0000>何<19\u0000>なに<1:\u0000>かヒントぐらいは<18\u0000>知<19\u0000>し<1:\u0000>っているだろう。",
			"hasEntryInOffsetOffsets": true,
			"noTerminator": false,
			"manualOffset": 0,
			"hasManualOffset": false
		},
		{
			"text_contents": "퇑턯야⟦DD27⟧⟦DEC0⟧⾶겼뺸⟦DDDE⟧뻄⟦DD27⟧⟦DEB6⟧콼뀧눯뀧별쌾쑼⟞⾰뚻뷞㸧얶␮慰敧퐤⟊糘밲껞캰슰즰똯⟦DA27⟧⿆㺷즸⟦DEB6⟧㉼솲쨧⟦DDDE⟧쀯⟦DBDE⟧딧⺶⟅뛆쬯⟦DD27⟧룄ퟞ⟦DCB2⟧밯쎯⟦D9B2⟧쀧⟦DBDE⟧⺵",
			"hasEntryInOffsetOffsets": true,
			"noTerminator": false,
			"manualOffset": 0,
			"hasManualOffset": false
		},
		{
			"text_contents": "なんだかな……なんだかなあ……。\nたく、どう<18\u0000>探<19\u0000>さが<1:\u0000>せっていうんですか。<1\"\u0000>\n……<17\u0003>{8, MessageNpcName, +}<2\u0001耀>{4, message}さんに<18\u0000>聞<19\u0000>き<1:\u0000>くのが<18\u0000>楽<19\u0000>らく<1:\u0000>ですよね。\n<18\u0000>情報通<19\u0000>じょうほうつう<1:\u0000>なんですから……。",
			"hasEntryInOffsetOffsets": true,
			"noTerminator": false,
			"manualOffset": 0,
			"hasManualOffset": false
		},
		{
			"text_contents": "⟅생뛞糅⟅생뛞냅쀮렧쑼⟞⾰뚻뻞꼧⿃뎲⟦DD27⟧⟦DEC3⟧㺽⺶瀤条⑥⑼敭獳条㩥敍獳条乥捰慎敭㈺㐱㐷㌸㐶㨹潶捩⑥⟦DDBB⟧⿆뢷⟉⟦DEB6⟧휯쎸⟞⾽죖밮껞캰슰⾰⟅쏝뷞똾⻗",
			"hasEntryInOffsetOffsets": true,
			"noTerminator": false,
			"manualOffset": 0,
			"hasManualOffset": false
		},
		{
			"text_contents": "じゃあ、<18\u0000>君<19\u0000>きみ<1:\u0000>は<18\u0000>疲<19\u0000>つか<1:\u0000>れているだろうし\nここで<18\u0000>待<19\u0000>ま<1:\u0000>っててね。",
			"hasEntryInOffsetOffsets": true,
			"noTerminator": false,
			"manualOffset": 0,
			"hasManualOffset": false
		},
		{
			"text_contents": "⟦DEBC⟧➬粰킷⿜㻂➶쏚⟦D9B2⟧⟦DEC0⟧뗛粼먲쎺⿞⟏쎯죃.",
			"hasEntryInOffsetOffsets": true,
			"noTerminator": true,
			"manualOffset": 0,
			"hasManualOffset": false
		},
		{
			"text_contents": "ひとまずあなたは<18\u0000>疲<19\u0000>つか<1:\u0000>れているでしょうから\nここで<18\u0000>待<19\u0000>ま<1:\u0000>っていてください。",
			"hasEntryInOffsetOffsets": true,
			"noTerminator": false,
			"manualOffset": 0,
			"hasManualOffset": false
		},
		{
			"text_contents": "㻋⟄뷏⿞얱쀧⿜㻂➶쏚⟦D9B2⟧⟦DEC3⟧꺼뚵糗먲쎺⿞⟏쎯쎲삸믞⺲",
			"hasEntryInOffsetOffsets": true,
			"noTerminator": false,
			"manualOffset": 0,
			"hasManualOffset": false
		},
		{
			"text_contents": "ひとまず<18\u0000>体<19\u0000>からだ<1:\u0000>を<18\u0000>休<19\u0000>やす<1:\u0000>めるのも<18\u0000>兼<19\u0000>か<1:\u0000>ねて\nあなたはここでお<18\u0000>待<19\u0000>ま<1:\u0000>ちください。",
			"hasEntryInOffsetOffsets": true,
			"noTerminator": false,
			"manualOffset": 0,
			"hasManualOffset": false
		},
		{
			"text_contents": "㻋⟄뷏⿞ힶ⟦DEC0⟧⾵뷔⟒짙⿓➶쏈㉼얱쀧⿜몺⟦DEC3⟧딯쇏렯⟦DEC0⟧➻⺲",
			"hasEntryInOffsetOffsets": true,
			"noTerminator": false,
			"manualOffset": 0,
			"hasManualOffset": false
		},
		{
			"text_contents": "んじゃまあ、あんたは<18\u0000>疲<19\u0000>つか<1:\u0000>れてるだろうし\nここで<18\u0000>待<19\u0000>ま<1:\u0000>ってな！",
			"hasEntryInOffsetOffsets": true,
			"noTerminator": false,
			"manualOffset": 0,
			"hasManualOffset": false
		},
		{
			"text_contents": "볝곞⟏粰➱생⿜㻂➶쏚샙⟦DBDE⟧벵⼾몺⟦DEC3⟧⟏쎯⻅",
			"hasEntryInOffsetOffsets": true,
			"noTerminator": false,
			"manualOffset": 0,
			"hasManualOffset": false
		},
		{
			"text_contents": "じゃあね、<18\u0000>僕<19\u0000>ぼく<1:\u0000><18\u0000>行<19\u0000>い<1:\u0000>くけど\n<18\u0000>君<19\u0000>きみ<1:\u0000>は<18\u0000>疲<19\u0000>つか<1:\u0000>れていると<18\u0000>思<19\u0000>おも<1:\u0000>うからここで<18\u0000>休<19\u0000>やす<1:\u0000>んでて。",
			"hasEntryInOffsetOffsets": true,
			"noTerminator": false,
			"manualOffset": 0,
			"hasManualOffset": false
		},
		{
			"text_contents": "⟦DEBC⟧➬좰칼⟞⾸뢲✾쒹糞뜲⟦DCD0⟧숯똾⟦DA27⟧닃쓙딯⟓뚳糗먲쎺⿞뷔⟦DD27⟧⟦DEC3⟧⻃",
			"hasEntryInOffsetOffsets": true,
			"noTerminator": false,
			"manualOffset": 0,
			"hasManualOffset": false
		},
		{
			"text_contents": "じゃあ、あなたはここで<18\u0000>待<19\u0000>ま<1:\u0000>ってなさいな。\n<18\u0000>疲<19\u0000>つか<1:\u0000>れてるでしょ？それがいいわ。",
			"hasEntryInOffsetOffsets": true,
			"noTerminator": false,
			"manualOffset": 0,
			"hasManualOffset": false
		},
		{
			"text_contents": "⟦DEBC⟧➬粰얱쀧⿜몺⟦DEC3⟧켯꼧엃늻⻅㻂➶쏚쏙볞㾮⟦DABF⟧⟦DEB6⟧눯뀧⟦DC2F⟧.",
			"hasEntryInOffsetOffsets": true,
			"noTerminator": true,
			"manualOffset": 0,
			"hasManualOffset": false
		},
		{
			"text_contents": "では<18\u0000>私<19\u0000>わたし<1:\u0000>は<18\u0000>行<19\u0000>い<1:\u0000>くが、<18\u0000>君<19\u0000>きみ<1:\u0000>は<18\u0000>疲<19\u0000>つか<1:\u0000>れているだろう。\nここで<18\u0000>休<19\u0000>やす<1:\u0000>んでいたまえ。",
			"hasEntryInOffsetOffsets": true,
			"noTerminator": false,
			"manualOffset": 0,
			"hasManualOffset": false
		},
		{
			"text_contents": "⟦DEC3⟧⟦DC27⟧ぼ샜⟦DCBC⟧눯➸⟦DEB6⟧라⟦DCD0⟧숯똾⟦DA27⟧닃샙⟦DBDE⟧⺵몺⟦DEC3⟧퐯➽쏝닞쿀⺴",
			"hasEntryInOffsetOffsets": true,
			"noTerminator": false,
			"manualOffset": 0,
			"hasManualOffset": false
		},
		{
			"text_contents": "では、ここで<18\u0000>待<19\u0000>ま<1:\u0000>っていてください……。\n<18\u0000>今<19\u0000>いま<1:\u0000>は<18\u0000>疲<19\u0000>つか<1:\u0000>れているでしょうから。",
			"hasEntryInOffsetOffsets": true,
			"noTerminator": false,
			"manualOffset": 0,
			"hasManualOffset": false
		},
		{
			"text_contents": "⟦DEC3⟧⟦DC27⟧멼쎺⿞⟏쎯쎲삸믞⺲➲⟦DCCF⟧숯똾⟦DA27⟧닃쏙볞떮ힶ.",
			"hasEntryInOffsetOffsets": true,
			"noTerminator": true,
			"manualOffset": 0,
			"hasManualOffset": false
		},
		{
			"text_contents": "……<18\u0000>考<19\u0000>かんが<1:\u0000>えたのだが、あの<18\u0000>憎<19\u0000>にく<1:\u0000>き<18\u0000>魔女<19\u0000>まじょ<1:\u0000>めに<18\u0000>直接<19\u0000>ちょくせつ<1:\u0000>\nひと<18\u0000>泡<19\u0000>あわ<1:\u0000>ふかしてやりたいケロ。<1\"\u0000>\nそれに<18\u0000>徹底的<19\u0000>てっていてき<1:\u0000>にヤツを<18\u0000>倒<19\u0000>たお<1:\u0000>さんと\n<18\u0000>元<19\u0000>もと<1:\u0000>の<18\u0000>姿<19\u0000>すがた<1:\u0000>を<18\u0000>取<19\u0000>と<1:\u0000>り<18\u0000>戻<19\u0000>もど<1:\u0000>せんかもしれんケロ。<1\"\u0000>\nここは<18\u0000>王子<19\u0000>おうじ<1:\u0000>たるオレ<18\u0000>様<19\u0000>さま<1:\u0000>がお<18\u0000>前<19\u0000>まえ<1:\u0000>を<18\u0000>導<19\u0000>みちび<1:\u0000>き\nこの<18\u0000>剣<19\u0000>けん<1:\u0000>を<18\u0000>存分<19\u0000>ぞんぶん<1:\u0000>に<18\u0000>奮<19\u0000>ふる<1:\u0000>おうではないかケロ！",
			"hasEntryInOffsetOffsets": true,
			"noTerminator": false,
			"manualOffset": 0,
			"hasManualOffset": false
		},
		{
			"text_contents": "",
			"hasEntryInOffsetOffsets": true,
			"noTerminator": false,
			"manualOffset": 0,
			"hasManualOffset": false
		},
		{
			"text_contents": "<18\u0000>良<19\u0000>よ<1:\u0000>い<18\u0000>判断<19\u0000>はんだん<1:\u0000>ケロ。\nでは、お<18\u0000>前<19\u0000>まえ<1:\u0000>の<18\u0000>島<19\u0000>しま<1:\u0000>へ<18\u0000>行<19\u0000>い<1:\u0000>ってるケロ！",
			"hasEntryInOffsetOffsets": true,
			"noTerminator": false,
			"manualOffset": 0,
			"hasManualOffset": false
		},
		{
			"text_contents": "",
			"hasEntryInOffsetOffsets": true,
			"noTerminator": false,
			"manualOffset": 0,
			"hasManualOffset": false
		},
		{
			"text_contents": "ケロッ！？お<18\u0000>前<19\u0000>まえ<1:\u0000>の<18\u0000>島<19\u0000>しま<1:\u0000>には\nオレ<18\u0000>様<19\u0000>さま<1:\u0000>が<18\u0000>住<19\u0000>す<1:\u0000>むスペースがないケロ！！<1\"\u0000>\n<18\u0000>空<19\u0000>あ<1:\u0000>きができ<18\u0000>次第<19\u0000>しだい<1:\u0000>、<18\u0000>連<19\u0000>つ<1:\u0000>れて<18\u0000>行<19\u0000>い<1:\u0000>くケロよ！",
			"hasEntryInOffsetOffsets": true,
			"noTerminator": false,
			"manualOffset": 0,
			"hasManualOffset": false
		},
		{
			"text_contents": "",
			"hasEntryInOffsetOffsets": true,
			"noTerminator": false,
			"manualOffset": 0,
			"hasManualOffset": false
		},
		{
			"text_contents": "なんと……オレ<18\u0000>様<19\u0000>さま<1:\u0000>の<18\u0000>誘<19\u0000>さそ<1:\u0000>いを<18\u0000>断<19\u0000>ことわ<1:\u0000>ったケロ！？\n……お<18\u0000>前<19\u0000>まえ<1:\u0000>、<18\u0000>気<19\u0000>き<1:\u0000>は<18\u0000>確<19\u0000>たし<1:\u0000>かかケロ？",
			"hasEntryInOffsetOffsets": true,
			"noTerminator": false,
			"manualOffset": 0,
			"hasManualOffset": false
		},
		{
			"text_contents": "",
			"hasEntryInOffsetOffsets": true,
			"noTerminator": false,
			"manualOffset": 0,
			"hasManualOffset": false
		},
		{
			"text_contents": "オレ<18\u0000>様<19\u0000>さま<1:\u0000>を「パーティー」に<18\u0000>加<19\u0000>くわ<1:\u0000>えれば\nお<18\u0000>前<19\u0000>まえ<1:\u0000>たちが<18\u0000>心強<19\u0000>こころづよ<1:\u0000>いケロ。なんてったって……。<1\"\u0000>\nバトル<18\u0000>中<19\u0000>ちゅう<1:\u0000>は「オート」で<18\u0000>攻撃<19\u0000>こうげき<1:\u0000>するケロ！\nしかも……。<1\"\u0000>\nバトル<18\u0000>中<19\u0000>ちゅう<1:\u0000>は「コマンド」でわざが<18\u0000>使<19\u0000>つか<1:\u0000>えるケロ！！\nただし、わざは……。<1\"\u0000>\n「<18\u0000>一度使<19\u0000>いちどつか<1:\u0000>うとしばらくのターン<18\u0000>使<19\u0000>つか<1:\u0000>えない」ケロ。\n<18\u0000>用法用量<19\u0000>ようほうようりょう<1:\u0000>に<18\u0000>気<19\u0000>き<1:\u0000>を<18\u0000>付<19\u0000>つ<1:\u0000>けて、<18\u0000>正<19\u0000>ただ<1:\u0000>しく<18\u0000>使<19\u0000>つか<1:\u0000>うケロ。<1\"\u0000>\nでは、オレ<18\u0000>様<19\u0000>さま<1:\u0000>は<18\u0000>電波人間<19\u0000>でんぱにんげん<1:\u0000>ボックスで\n<18\u0000>待<19\u0000>ま<1:\u0000>っているケロ！",
			"hasEntryInOffsetOffsets": true,
			"noTerminator": false,
			"manualOffset": 0,
			"hasManualOffset": false
		},
		{
			"text_contents": "",
			"hasEntryInOffsetOffsets": true,
			"noTerminator": false,
			"manualOffset": 0,
			"hasManualOffset": false
		},
		{
			"text_contents": "<18\u0000>電波人間<19\u0000>でんぱにんげん<1:\u0000>ボックスに<18\u0000>空<19\u0000>あ<1:\u0000>きができたら\nまたオレ<18\u0000>様<19\u0000>さま<1:\u0000>に<18\u0000>声<19\u0000>こえ<1:\u0000>をかけるケロ。<1\"\u0000>\nお<18\u0000>前<19\u0000>まえ<1:\u0000>の<18\u0000>旅路<19\u0000>たびじ<1:\u0000>を<18\u0000>導<19\u0000>みちび<1:\u0000>くのもまた<18\u0000>我<19\u0000>わ<1:\u0000>が<18\u0000>運命<19\u0000>さだめ<1:\u0000>……\nあまり<18\u0000>長<19\u0000>なが<1:\u0000>く<18\u0000>待<19\u0000>ま<1:\u0000>たせるではないケロよ！！",
			"hasEntryInOffsetOffsets": true,
			"noTerminator": false,
			"manualOffset": 0,
			"hasManualOffset": false
		},
		{
			"text_contents": "",
			"hasEntryInOffsetOffsets": true,
			"noTerminator": false,
			"manualOffset": 0,
			"hasManualOffset": false
		},
		{
			"text_contents": "やはりオレ<18\u0000>様<19\u0000>さま<1:\u0000>の<18\u0000>導<19\u0000>みちび<1:\u0000>きが<18\u0000>必要<19\u0000>ひつよう<1:\u0000>かケロ！？<1\"\u0000>\n<18\u0000>良<19\u0000>よ<1:\u0000>いケロ<18\u0000>良<19\u0000>よ<1:\u0000>いケロ。\nさあ、オレ<18\u0000>様<19\u0000>さま<1:\u0000>も<18\u0000>共<19\u0000>とも<1:\u0000>に<18\u0000>行<19\u0000>い<1:\u0000>くケロ！！",
			"hasEntryInOffsetOffsets": true,
			"noTerminator": false,
			"manualOffset": 0,
			"hasManualOffset": false
		},
		{
			"text_contents": "",
			"hasEntryInOffsetOffsets": true,
			"noTerminator": false,
			"manualOffset": 0,
			"hasManualOffset": false
		},
		{
			"text_contents": "<18\u0000>待<19\u0000>ま<1:\u0000>つケロ。\n<18\u0000>大事<19\u0000>だいじ<1:\u0000>な<18\u0000>話<19\u0000>はなし<1:\u0000>があるケロ。",
			"hasEntryInOffsetOffsets": true,
			"noTerminator": false,
			"manualOffset": 0,
			"hasManualOffset": false
		},
		{
			"text_contents": "",
			"hasEntryInOffsetOffsets": true,
			"noTerminator": false,
			"manualOffset": 0,
			"hasManualOffset": false
		},
		{
			"text_contents": "あった！\nこれが<17\u0003>{8, MessageNpcName, +}<2\u0001耀>{4, message}さんの<18\u0000>落<19\u0000>おと<1:\u0000>し<18\u0000>物<19\u0000>もの<1:\u0000>だよ！！<1\"\u0000>\nさあ、<18\u0000>島<19\u0000>しま<1:\u0000>に<18\u0000>帰<19\u0000>かえ<1:\u0000>って<18\u0000>渡<19\u0000>わた<1:\u0000>してあげよう！<1\"\u0000>\nそれと、カエルさんに<18\u0000>頼<19\u0000>たの<1:\u0000>まれた\n「オーブ」<18\u0000>集<19\u0000>あつ<1:\u0000>めもしないと。<1\"\u0000>\nう～ん……\nなんだか<18\u0000>大変<19\u0000>たいへん<1:\u0000>なことになっちゃったね……。",
			"hasEntryInOffsetOffsets": true,
			"noTerminator": false,
			"manualOffset": 0,
			"hasManualOffset": false
		},
		{
			"text_contents": "➱삯멼뛚⿞洤獥慳敧䴺獥慳敧灎乣浡㩥ㄲ㜴㠴㘳㤴瘺楯散묤짝딯별짓⟦DEC0⟧혧⑼慰敧⼤➻粰쾼옧똯됧쎯⟦DC2F⟧⟀㺼뇃⟦DEB9⟧⟖粰瀤条⑥뼯쓚뙼⟦D9B4⟧⟦DDBB⟧⿆지⟏샚땼첰뇞틂팧밯닅⻄瀤条⑥댯⟦DDB0⟧야⟦DD27⟧⟦DEC0⟧⾶닀⟦DDCD⟧뫅⟄⿆⟅솯꾬죀.",
			"hasEntryInOffsetOffsets": true,
			"noTerminator": true,
			"manualOffset": 0,
			"hasManualOffset": false
		},
		{
			"text_contents": "ありました！\nこれが<17\u0003>{8, MessageNpcName, +}<2\u0001耀>{4, message}さんの<18\u0000>落<19\u0000>おと<1:\u0000>し<18\u0000>物<19\u0000>もの<1:\u0000>ですよ！<1\"\u0000>\n<18\u0000>早<19\u0000>はや<1:\u0000>く<18\u0000>島<19\u0000>しま<1:\u0000>に<18\u0000>帰<19\u0000>かえ<1:\u0000>って<18\u0000>渡<19\u0000>わた<1:\u0000>しましょう！<1\"\u0000>\nそれと、カエルさんに<18\u0000>頼<19\u0000>たの<1:\u0000>まれた\n「オーブ」<18\u0000>集<19\u0000>あつ<1:\u0000>めをしないといけませんね。<1\"\u0000>\nうーん……\nなんだか<18\u0000>大変<19\u0000>たいへん<1:\u0000>なことになりましたね……。",
			"hasEntryInOffsetOffsets": true,
			"noTerminator": false,
			"manualOffset": 0,
			"hasManualOffset": false
		},
		{
			"text_contents": "⟦D8B1⟧⟏㺼糀⟦DABA⟧⟦DEB6⟧␯敭獳条㩥敍獳条乥捰慎敭㈺㐱㐷㌸㐶㨹潶捩⑥⟦DDBB⟧⿉쒵펼쏉⟞횽⑼慰敧쨤퐧⾸쾼옧똯됧쎯⟦DC2F⟧변볏➮粵瀤条⑥뼯쓚뙼⟦D9B4⟧⟦DDBB⟧⿆지⟏샚땼첰뇞틂딧밯⟅쒲눯쾹➾죝␮慰敧⼤➳⟦DDB0⟧야⟦DD27⟧⟦DEC0⟧⾶닀⟦DDCD⟧뫅⟄⿆⟦D8C5⟧⟏밳쀾⻈",
			"hasEntryInOffsetOffsets": true,
			"noTerminator": false,
			"manualOffset": 0,
			"hasManualOffset": false
		},
		{
			"text_contents": "ありましたね！\nこれが<17\u0003>{8, MessageNpcName, +}<2\u0001耀>{4, message}さんの<18\u0000>落<19\u0000>おと<1:\u0000>し<18\u0000>物<19\u0000>もの<1:\u0000>でしょう！<1\"\u0000>\n<18\u0000>早速<19\u0000>さっそく<1:\u0000><18\u0000>島<19\u0000>しま<1:\u0000>に<18\u0000>帰<19\u0000>かえ<1:\u0000>って<18\u0000>渡<19\u0000>わた<1:\u0000>しましょう！<1\"\u0000>\nそして<18\u0000>次<19\u0000>つぎ<1:\u0000>はカエルさんに<18\u0000>頼<19\u0000>たの<1:\u0000>まれた\n「オーブ」<18\u0000>集<19\u0000>あつ<1:\u0000>めですね……。<1\"\u0000>\nなんと<18\u0000>言<19\u0000>い<1:\u0000>いますか……\n<18\u0000>大変<19\u0000>たいへん<1:\u0000>なことになりましたね……。",
			"hasEntryInOffsetOffsets": true,
			"noTerminator": false,
			"manualOffset": 0,
			"hasManualOffset": false
		},
		{
			"text_contents": "⟦D8B1⟧⟏㺼죀멼뛚⿞洤獥慳敧䴺獥慳敧灎乣浡㩥ㄲ㜴㠴㘳㤴瘺楯散묤짝딯별짓⟦DEC3⟧꺼딧⑼慰敧⼤꾻뢿밯⟏⿆➶꾴⿃샜쾼꺼딧⑼慰敧⼤벿쌾숯⟦DEB7⟧⟦DC27⟧뙼⟦D9B4⟧⟦DDBB⟧⿆지⟏샚딯첰뇞숧⿒⟦DEC3⟧좽␮慰敧씤⟦DD27⟧⿄낲뷏똾쁼춲엝쒺옧씯쿘㌧㺼죀.",
			"hasEntryInOffsetOffsets": true,
			"noTerminator": true,
			"manualOffset": 0,
			"hasManualOffset": false
		},
		{
			"text_contents": "みーっけ！\nこれが<17\u0003>{8, MessageNpcName, +}<2\u0001耀>{4, message}さんの<18\u0000>落<19\u0000>おと<1:\u0000>し<18\u0000>物<19\u0000>もの<1:\u0000>で<18\u0000>間違<19\u0000>まちが<1:\u0000>いなし！<1\"\u0000>\nすぐ<18\u0000>島<19\u0000>しま<1:\u0000>に<18\u0000>帰<19\u0000>かえ<1:\u0000>って<18\u0000>渡<19\u0000>わた<1:\u0000>してやろうぜ！<1\"\u0000>\nそれで<18\u0000>次<19\u0000>つぎ<1:\u0000>はカエル<18\u0000>王子<19\u0000>おうじ<1:\u0000>に<18\u0000>頼<19\u0000>たの<1:\u0000>まれた\n「オーブ」<18\u0000>集<19\u0000>あつ<1:\u0000>めか……。<1\"\u0000>\nまあ<18\u0000>見<19\u0000>み<1:\u0000>つけるって<18\u0000>言<19\u0000>い<1:\u0000>っちまったけど\n<18\u0000>大変<19\u0000>たいへん<1:\u0000>なことになったな……。",
			"hasEntryInOffsetOffsets": true,
			"noTerminator": false,
			"manualOffset": 0,
			"hasManualOffset": false
		},
		{
			"text_contents": "⟐릯멼뛚⿞洤獥慳敧䴺獥慳敧灎乣浡㩥ㄲ㜴㠴㘳㤴瘺楯散묤짝딯별짓⟦DEC3⟧켯뛁⟞얲밧簾瀤条⑥➽⟦DEB8⟧밯⟏⿆➶꾴⿃샜㺼⿃⟦DBD4⟧딧븯糞瀤条⑥뼯쏚⿞럂⟞糜똲⟦D9B4⟧➵벰웞쀯쿉⟦DA27⟧⿀낵⟦DECC⟧슱⟒⺶瀤条⑥켯粰퀲㻂⟦D9B9⟧쎯눯솯꿏⟀쒹糞쀲춲엝쒺옧씯꼧엀.",
			"hasEntryInOffsetOffsets": true,
			"noTerminator": true,
			"manualOffset": 0,
			"hasManualOffset": false
		},
		{
			"text_contents": "みつけたー！\nこれだよね！<17\u0003>{8, MessageNpcName, +}<2\u0001耀>{4, message}さんの<18\u0000>落<19\u0000>おと<1:\u0000>し<18\u0000>物<19\u0000>もの<1:\u0000>！<1\"\u0000>\n<18\u0000>早<19\u0000>はや<1:\u0000>く<18\u0000>島<19\u0000>しま<1:\u0000>に<18\u0000>帰<19\u0000>かえ<1:\u0000>って<18\u0000>渡<19\u0000>わた<1:\u0000>してあげようね！<1\"\u0000>\nそれで<18\u0000>次<19\u0000>つぎ<1:\u0000>はカエルさんに<18\u0000>頼<19\u0000>たの<1:\u0000>まれた\n「オーブ」<18\u0000>探<19\u0000>さが<1:\u0000>し……だよね。<1\"\u0000>\n<18\u0000>大変<19\u0000>たいへん<1:\u0000>なことになっちゃったな……。",
			"hasEntryInOffsetOffsets": true,
			"noTerminator": false,
			"manualOffset": 0,
			"hasManualOffset": false
		},
		{
			"text_contents": "싐뤾냀멼샚⟞죖⑼敭獳条㩥敍獳条乥捰慎敭㈺㐱㐷㌸㐶㨹潶捩⑥⟦DDBB⟧⿉쒵펼糉瀤条⑥⟊룔밯⟏⿆➶꾴⿃샜㺼⿃릱훞뀧糈瀤条⑥뼯쏚⿞럂⟞糜뒶믙웝쀯쿉⟦DA27⟧糀딲첰믞똧볞쀯훞㿈瀤条⑥쀯춲엝쒺옧씯꼧곁삯⻅",
			"hasEntryInOffsetOffsets": true,
			"noTerminator": false,
			"manualOffset": 0,
			"hasManualOffset": false
		},
		{
			"text_contents": "これよー！！\nこれが<17\u0003>{8, MessageNpcName, +}<2\u0001耀>{4, message}さんの<18\u0000>落<19\u0000>おと<1:\u0000>し<18\u0000>物<19\u0000>もの<1:\u0000>だわー！<1\"\u0000>\n<18\u0000>早<19\u0000>はや<1:\u0000>く<18\u0000>島<19\u0000>しま<1:\u0000>に<18\u0000>帰<19\u0000>かえ<1:\u0000>りましょう。\n<18\u0000>渡<19\u0000>わた<1:\u0000>してあげなきゃ！<1\"\u0000>\nそれでカエルの<18\u0000>王子様<19\u0000>おうじさま<1:\u0000>に<18\u0000>頼<19\u0000>たの<1:\u0000>まれた\n「オーブ」<18\u0000>探<19\u0000>さが<1:\u0000>しが<18\u0000>待<19\u0000>ま<1:\u0000>ってるわ。<1\"\u0000>\n<18\u0000>流<19\u0000>なが<1:\u0000>れの<18\u0000>雰囲気<19\u0000>ふんいき<1:\u0000>で<18\u0000>引<19\u0000>ひ<1:\u0000>き<18\u0000>受<19\u0000>う<1:\u0000>けちゃったけど\n<18\u0000>大変<19\u0000>たいへん<1:\u0000>なことになってきたわね……。",
			"hasEntryInOffsetOffsets": true,
			"noTerminator": false,
			"manualOffset": 0,
			"hasManualOffset": false
		},
		{
			"text_contents": "⟦DABA⟧⟖粰⟦DABA⟧⟦DEB6⟧␯敭獳条㩥敍獳条乥捰慎敭㈺㐱㐷㌸㐶㨹潶捩⑥⟦DDBB⟧⿉쒵펼색⟞냜⑼慰敧쨤퐧⾸쾼옧똯⟦D8B4⟧볏➮⺵샜㺼⿃릱엞뜧粬瀤条⑥뼯쏚糞똲⟦D9B4⟧⿉➵벰믞웏쀯쿉⟦DA27⟧糀낵⟦DECC⟧➻⟦DEB6⟧뚼⿞⟏쎯⿙⻜瀤条⑥씯⟦DEB6⟧짚찯㻝➲쎷糞쬲뜾➳솹꾬맀⟦DEC4⟧㉼닀⟦DDCD⟧뫅⟄없쎯뜯✾⟦DCC0⟧⻈",
			"hasEntryInOffsetOffsets": true,
			"noTerminator": false,
			"manualOffset": 0,
			"hasManualOffset": false
		},
		{
			"text_contents": "<18\u0000>見<19\u0000>み<1:\u0000>つけたぞ！\nこれが<18\u0000>彼<19\u0000>かれ<1:\u0000>の<18\u0000>言<19\u0000>い<1:\u0000>っていた<18\u0000>落<19\u0000>おと<1:\u0000>し<18\u0000>物<19\u0000>もの<1:\u0000>だろう！<1\"\u0000>\n<18\u0000>早速<19\u0000>さっそく<1:\u0000><18\u0000>島<19\u0000>しま<1:\u0000>に<18\u0000>帰<19\u0000>かえ<1:\u0000>って<18\u0000>渡<19\u0000>わた<1:\u0000>そうではないか。<1\"\u0000>\nただ……\n<18\u0000>次<19\u0000>つぎ<1:\u0000>は<18\u0000>頼<19\u0000>たの<1:\u0000>まれた「オーブ」<18\u0000>探<19\u0000>さが<1:\u0000>しか。<1\"\u0000>\nふーむ。\nなかなか<18\u0000>大変<19\u0000>たいへん<1:\u0000>なことになってきたな。",
			"hasEntryInOffsetOffsets": true,
			"noTerminator": false,
			"manualOffset": 0,
			"hasManualOffset": false
		},
		{
			"text_contents": "싐뤾뿀糞⟦DABA⟧똯뛞⟚⿉꾲닃⿀쒵펼색⟦DBDE⟧딧⑼慰敧⼤꾻뢿簾배⟏⿆➶꾴⿃샜➿쎵⟦DCDE⟧씯눧⺶瀤条⑥쀯쀧糞럂⟞⿜지⟏샚딯첰믞똧볞똾␮慰敧⼤⟌톰씮얶⾶닀⟦DDCD⟧뫅⟄⿆⟅쎯㺷엀.",
			"hasEntryInOffsetOffsets": true,
			"noTerminator": true,
			"manualOffset": 0,
			"hasManualOffset": false
		},
		{
			"text_contents": "はあ……ありましたね。\nこれが<17\u0003>{8, MessageNpcName, +}<2\u0001耀>{4, message}さんの<18\u0000>落<19\u0000>おと<1:\u0000>し<18\u0000>物<19\u0000>もの<1:\u0000>でしょう。<1\"\u0000>\n<18\u0000>早<19\u0000>はや<1:\u0000>く<18\u0000>島<19\u0000>しま<1:\u0000>に<18\u0000>帰<19\u0000>かえ<1:\u0000>って<18\u0000>渡<19\u0000>わた<1:\u0000>してしまいましょう。<1\"\u0000>\nああでも、<18\u0000>次<19\u0000>つぎ<1:\u0000>はカエルさんに<18\u0000>頼<19\u0000>たの<1:\u0000>まれた\n「オーブ」<18\u0000>探<19\u0000>さが<1:\u0000>しがあるのか……。<1\"\u0000>\nはあ……\n<18\u0000>大変<19\u0000>たいへん<1:\u0000>なことになってきましたね……。",
			"hasEntryInOffsetOffsets": true,
			"noTerminator": false,
			"manualOffset": 0,
			"hasManualOffset": false
		},
		{
			"text_contents": "⟊粰⟦D8B1⟧⟏㺼죀먮뛚⿞洤獥慳敧䴺獥慳敧灎乣浡㩥ㄲ㜴㠴㘳㤴瘺楯散묤짝딯별짓⟦DEC3⟧꺼딧␮慰敧쨤퐧㺸쾼옧똯됧쎯⟦DC2F⟧변쌾쾼쾲꺼딧␮慰敧⼤➱⾰⟦DEC3⟧팧쉼⟦DEB7⟧⟦DC27⟧똯⟦D9B4⟧⟦DDBB⟧⿆지⟏샚땼첰믞똧볞⟦DEB6⟧넯⟦D927⟧뛉␮慰敧쨤粱쀲춲엝쒺옧씯꼧⿃쾷밧쀾⻈",
			"hasEntryInOffsetOffsets": true,
			"noTerminator": false,
			"manualOffset": 0,
			"hasManualOffset": false
		},
		{
			"text_contents": "",
			"hasEntryInOffsetOffsets": false,
			"noTerminator": false,
			"manualOffset": 0,
			"hasManualOffset": true
		}
	],
	"old_string_data": [],
	"v2_string_data": [],
	"v4_string_data": [],
	"v5_string_data": [],
	"v6_string_data": {
		"Unk1Sig": 0,
		"Unk2Sig": 0,
		"Unk3Sig": 0,
		"Unk4Sig": 0,
		"offset_data": []
	},
	"v3_string_data": [
		3503345664,
		3503345682,
		3503345682,
		3503345665,
		3503345666,
		3503345667,
		3503345668,
		3503345669,
		3503345670,
		3503345671,
		3503345672,
		3503345665,
		3503345666,
		3503345667,
		3503345668,
		3503345669,
		3503345670,
		3503345671,
		3503345672,
		3503345665,
		3503345666,
		3503345667,
		3503345668,
		3503345669,
		3503345670,
		3503345671,
		3503345672,
		3503345665,
		3503345666,
		3503345667,
		3503345668,
		3503345669,
		3503345670,
		3503345671,
		3503345672,
		3503345686,
		3503345665,
		3503345666,
		3503345667,
		3503345668,
		3503345669,
		3503345670,
		3503345671,
		3503345672,
		3503345665,
		3503345666,
		3503345667,
		3503345668,
		3503345669,
		3503345670,
		3503345671,
		3503345672,
		3503345686,
		3503345665,
		3503345666,
		3503345667,
		3503345668,
		3503345669,
		3503345670,
		3503345671,
		3503345672,
		3503345686,
		3503345686,
		3503345665,
		3503345666,
		3503345667,
		3503345668,
		3503345669,
		3503345670,
		3503345671,
		3503345672,
		3503345686,
		3503345665,
		3503345666,
		3503345667,
		3503345668,
		3503345669,
		3503345670,
		3503345671,
		3503345672,
		3503345665,
		3503345666,
		3503345667,
		3503345668,
		3503345669,
		3503345670,
		3503345671,
		3503345672,
		3503345686,
		3503345665,
		3503345666,
		3503345667,
		3503345668,
		3503345669,
		3503345670,
		3503345671,
		3503345672,
		3503345686,
		3503345665,
		3503345666,
		3503345667,
		3503345668,
		3503345669,
		3503345670,
		3503345671,
		3503345672,
		3503345686,
		3503345686,
		3503345686,
		3503345665,
		3503345666,
		3503345667,
		3503345668,
		3503345669,
		3503345670,
		3503345671,
		3503345672,
		3503345665,
		3503345666,
		3503345667,
		3503345668,
		3503345669,
		3503345670,
		3503345671,
		3503345672,
		3503345686,
		3503345686,
		3503345686,
		3503345686,
		3503345686,
		3503345686,
		3503345686,
		3503345686,
		3503345665,
		3503345666,
		3503345667,
		3503345668,
		3503345669,
		3503345670,
		3503345671,
		3503345672
	],
	"attributes": {
		"attributeStrings": [
			"message",
			"voice",
			"d01_msg"
		],
		"attributePairs": [
			{
				"attribute": "message",
				"value": 0
			},
			{
				"attribute": "voice",
				"value": 4
			}
		]
	},
	"flags": [
		2147483650,
		2147483826,
		2147483827,
		2147483651,
		2147483652,
		2147483653,
		2147483654,
		2147483655,
		2147483656,
		2147483657,
		2147483658,
		2147483659,
		2147483660,
		2147483661,
		2147483662,
		2147483663,
		2147483664,
		2147483665,
		2147483666,
		2147483667,
		2147483668,
		2147483669,
		2147483670,
		2147483671,
		2147483672,
		2147483673,
		2147483674,
		2147483675,
		2147483676,
		2147483677,
		2147483678,
		2147483679,
		2147483680,
		2147483681,
		2147483682,
		2147483683,
		2147483684,
		2147483685,
		2147483686,
		2147483687,
		2147483688,
		2147483689,
		2147483690,
		2147483691,
		2147483692,
		2147483693,
		2147483694,
		2147483695,
		2147483696,
		2147483697,
		2147483698,
		2147483699,
		2147483709,
		2147483710,
		2147483711,
		2147483712,
		2147483713,
		2147483714,
		2147483715,
		2147483716,
		2147483717,
		2147483718,
		2147483728,
		2147483729,
		2147483730,
		2147483731,
		2147483732,
		2147483733,
		2147483734,
		2147483735,
		2147483736,
		2147483737,
		2147483747,
		2147483748,
		2147483749,
		2147483750,
		2147483751,
		2147483752,
		2147483753,
		2147483754,
		2147483755,
		2147483756,
		2147483757,
		2147483758,
		2147483759,
		2147483760,
		2147483761,
		2147483762,
		2147483763,
		2147483764,
		2147483765,
		2147483766,
		2147483767,
		2147483768,
		2147483769,
		2147483770,
		2147483771,
		2147483772,
		2147483773,
		2147483774,
		2147483775,
		2147483776,
		2147483777,
		2147483778,
		2147483779,
		2147483780,
		2147483781,
		2147483782,
		2147483783,
		2147483793,
		2147483794,
		2147483795,
		2147483796,
		2147483797,
		2147483798,
		2147483799,
		2147483800,
		2147483801,
		2147483802,
		2147483803,
		2147483804,
		2147483805,
		2147483806,
		2147483807,
		2147483808,
		2147483809,
		2147483810,
		2147483811,
		2147483812,
		2147483813,
		2147483814,
		2147483815,
		2147483824,
		2147483816,
		2147483817,
		2147483818,
		2147483819,
		2147483820,
		2147483821,
		2147483822,
		2147483823
	]
}
